{"enemySlots": [2, 1, 0, 0, 0, 2, 1, 0, 0, 0, 0], "alternatives": {"Dark Souls The Board Game,Iron Keep,Painted World of Ariamis,Tomb of Giants,Darkroot": [[14, 30, 7, 22, 3, 7, 7, 7], [30, 22, 7, 3, 27, 7, 7, 7], [30, 24, 7, 3, 27, 7, 7, 7], [14, 30, 7, 8, 3, 7, 7, 7], [30, 8, 7, 3, 27, 7, 7, 7], [14, 30, 7, 24, 3, 7, 7, 7]], "Dark Souls The Board Game,Painted World of Ariamis,Tomb of Giants,Iron Keep": [[21, 30, 7, 3, 27, 7, 7, 7], [14, 9, 7, 30, 3, 7, 7, 7], [14, 30, 7, 30, 3, 7, 7, 7], [14, 30, 7, 3, 3, 7, 7, 7], [14, 30, 7, 3, 5, 7, 7, 7], [14, 21, 7, 30, 3, 7, 7, 7], [9, 30, 7, 3, 27, 7, 7, 7], [14, 30, 7, 3, 27, 7, 7, 7], [14, 14, 7, 30, 3, 7, 7, 7], [30, 3, 7, 27, 27, 7, 7, 7], [30, 30, 7, 3, 27, 7, 7, 7], [30, 3, 7, 3, 27, 7, 7, 7]], "Dark Souls The Board Game,Executioner Chariot,Iron Keep,Painted World of Ariamis,Tomb of Giants": [[10, 30, 7, 3, 27, 7, 7, 7], [14, 10, 7, 30, 3, 7, 7, 7]], "Dark Souls The Board Game,Explorers,Iron Keep,Painted World of Ariamis,Tomb of Giants": [[14, 30, 7, 3, 26, 7, 7, 7], [30, 3, 7, 26, 27, 7, 7, 7]], "Painted World of Ariamis,Tomb of Giants,Darkroot,Iron Keep": [[30, 8, 7, 3, 5, 7, 7, 7], [30, 30, 7, 8, 3, 7, 7, 7], [30, 24, 7, 3, 3, 7, 7, 7], [9, 30, 7, 22, 3, 7, 7, 7], [9, 30, 7, 8, 3, 7, 7, 7], [9, 30, 7, 24, 3, 7, 7, 7], [30, 8, 7, 3, 3, 7, 7, 7], [30, 8, 7, 24, 3, 7, 7, 7], [21, 30, 7, 24, 3, 7, 7, 7], [30, 24, 7, 3, 5, 7, 7, 7], [21, 30, 7, 8, 3, 7, 7, 7], [30, 8, 7, 22, 3, 7, 7, 7], [30, 24, 7, 22, 3, 7, 7, 7], [30, 30, 7, 22, 3, 7, 7, 7], [21, 30, 7, 22, 3, 7, 7, 7], [30, 22, 7, 3, 3, 7, 7, 7], [30, 22, 7, 22, 3, 7, 7, 7], [30, 22, 7, 3, 5, 7, 7, 7], [30, 8, 7, 8, 3, 7, 7, 7], [30, 24, 7, 24, 3, 7, 7, 7], [30, 30, 7, 24, 3, 7, 7, 7]], "Executioner Chariot,Iron Keep,Painted World of Ariamis,Tomb of Giants,Darkroot": [[10, 30, 7, 24, 3, 7, 7, 7], [10, 30, 7, 22, 3, 7, 7, 7], [10, 30, 7, 8, 3, 7, 7, 7]], "Explorers,Iron Keep,Painted World of Ariamis,Tomb of Giants,Darkroot": [[30, 24, 7, 3, 26, 7, 7, 7], [30, 22, 7, 3, 26, 7, 7, 7], [30, 8, 7, 3, 26, 7, 7, 7]], "Painted World of Ariamis,Tomb of Giants,Iron Keep": [[21, 30, 7, 30, 3, 7, 7, 7], [30, 30, 7, 3, 5, 7, 7, 7], [21, 21, 7, 30, 3, 7, 7, 7], [21, 9, 7, 30, 3, 7, 7, 7], [9, 30, 7, 30, 3, 7, 7, 7], [9, 30, 7, 3, 5, 7, 7, 7], [21, 30, 7, 3, 5, 7, 7, 7], [9, 9, 7, 30, 3, 7, 7, 7], [30, 30, 7, 3, 3, 7, 7, 7], [9, 30, 7, 3, 3, 7, 7, 7], [30, 3, 7, 3, 5, 7, 7, 7], [30, 3, 7, 3, 3, 7, 7, 7], [21, 30, 7, 3, 3, 7, 7, 7], [30, 30, 7, 30, 3, 7, 7, 7]], "Painted World of Ariamis,Tomb of Giants,Iron Keep,Executioner Chariot": [[10, 30, 7, 3, 5, 7, 7, 7], [9, 10, 7, 30, 3, 7, 7, 7], [21, 10, 7, 30, 3, 7, 7, 7], [10, 30, 7, 3, 3, 7, 7, 7], [10, 30, 7, 30, 3, 7, 7, 7], [10, 10, 7, 30, 3, 7, 7, 7]], "Explorers,Painted World of Ariamis,Tomb of Giants,Iron Keep": [[21, 30, 7, 3, 26, 7, 7, 7], [9, 30, 7, 3, 26, 7, 7, 7], [30, 30, 7, 3, 26, 7, 7, 7], [30, 3, 7, 3, 26, 7, 7, 7], [30, 3, 7, 26, 26, 7, 7, 7]], "Explorers,Executioner Chariot,Iron Keep,Painted World of Ariamis,Tomb of Giants": [[10, 30, 7, 3, 26, 7, 7, 7]], "Dark Souls The Board Game,Painted World of Ariamis,Tomb of Giants,Darkroot": [[14, 30, 7, 30, 24, 7, 7, 7], [14, 30, 7, 30, 8, 7, 7, 7], [9, 30, 7, 8, 27, 7, 7, 7], [14, 30, 7, 8, 22, 7, 7, 7], [30, 30, 7, 24, 27, 7, 7, 7], [14, 21, 7, 30, 24, 7, 7, 7], [14, 30, 7, 24, 22, 7, 7, 7], [9, 30, 7, 22, 27, 7, 7, 7], [14, 14, 7, 30, 22, 7, 7, 7], [14, 30, 7, 30, 22, 7, 7, 7], [14, 14, 7, 30, 24, 7, 7, 7], [21, 30, 7, 24, 27, 7, 7, 7], [14, 30, 7, 8, 27, 7, 7, 7], [14, 30, 7, 8, 24, 7, 7, 7], [30, 22, 7, 22, 27, 7, 7, 7], [14, 30, 7, 22, 27, 7, 7, 7], [14, 21, 7, 30, 22, 7, 7, 7], [30, 22, 7, 27, 27, 7, 7, 7], [14, 9, 7, 30, 8, 7, 7, 7], [30, 24, 7, 22, 27, 7, 7, 7], [21, 30, 7, 22, 27, 7, 7, 7], [14, 30, 7, 8, 5, 7, 7, 7], [14, 9, 7, 30, 22, 7, 7, 7], [14, 14, 7, 30, 8, 7, 7, 7], [14, 30, 7, 24, 24, 7, 7, 7], [14, 30, 7, 22, 22, 7, 7, 7], [30, 24, 7, 27, 27, 7, 7, 7], [30, 24, 7, 24, 27, 7, 7, 7], [14, 9, 7, 30, 24, 7, 7, 7], [14, 21, 7, 30, 8, 7, 7, 7], [9, 30, 7, 24, 27, 7, 7, 7], [30, 8, 7, 27, 27, 7, 7, 7], [21, 30, 7, 8, 27, 7, 7, 7], [14, 30, 7, 24, 5, 7, 7, 7], [30, 8, 7, 24, 27, 7, 7, 7], [30, 8, 7, 8, 27, 7, 7, 7], [30, 8, 7, 22, 27, 7, 7, 7], [14, 30, 7, 22, 5, 7, 7, 7], [30, 30, 7, 8, 27, 7, 7, 7], [14, 30, 7, 8, 8, 7, 7, 7], [14, 30, 7, 24, 27, 7, 7, 7]], "Dark Souls The Board Game,Executioner Chariot,Painted World of Ariamis,Tomb of Giants,Darkroot": [[14, 10, 7, 30, 24, 7, 7, 7], [14, 10, 7, 30, 22, 7, 7, 7], [10, 30, 7, 24, 27, 7, 7, 7], [10, 30, 7, 8, 27, 7, 7, 7], [14, 10, 7, 30, 8, 7, 7, 7], [10, 30, 7, 22, 27, 7, 7, 7]], "Dark Souls The Board Game,Explorers,Painted World of Ariamis,Tomb of Giants,Darkroot": [[14, 30, 7, 22, 26, 7, 7, 7], [30, 8, 7, 26, 27, 7, 7, 7], [30, 22, 7, 26, 27, 7, 7, 7], [14, 30, 7, 8, 26, 7, 7, 7], [30, 24, 7, 26, 27, 7, 7, 7], [14, 30, 7, 24, 26, 7, 7, 7]], "Dark Souls The Board Game,Painted World of Ariamis,Tomb of Giants": [[14, 14, 7, 30, 30, 7, 7, 7], [14, 14, 7, 14, 30, 7, 7, 7], [14, 21, 7, 30, 27, 7, 7, 7], [21, 9, 7, 30, 27, 7, 7, 7], [14, 9, 7, 30, 5, 7, 7, 7], [14, 30, 7, 30, 30, 7, 7, 7], [14, 14, 7, 30, 5, 7, 7, 7], [14, 30, 7, 27, 27, 7, 7, 7], [14, 9, 7, 30, 27, 7, 7, 7], [14, 30, 7, 30, 5, 7, 7, 7], [21, 30, 7, 27, 27, 7, 7, 7], [14, 14, 7, 9, 30, 7, 7, 7], [14, 30, 7, 30, 27, 7, 7, 7], [30, 30, 7, 30, 27, 7, 7, 7], [9, 9, 7, 30, 27, 7, 7, 7], [14, 9, 7, 30, 30, 7, 7, 7], [14, 14, 7, 30, 27, 7, 7, 7], [21, 30, 7, 30, 27, 7, 7, 7], [14, 21, 7, 30, 30, 7, 7, 7], [14, 21, 7, 21, 30, 7, 7, 7], [14, 21, 7, 30, 5, 7, 7, 7], [9, 30, 7, 27, 27, 7, 7, 7], [14, 21, 7, 9, 30, 7, 7, 7], [9, 30, 7, 30, 27, 7, 7, 7], [30, 30, 7, 27, 27, 7, 7, 7], [14, 9, 7, 9, 30, 7, 7, 7], [14, 14, 7, 21, 30, 7, 7, 7], [21, 21, 7, 30, 27, 7, 7, 7]], "Dark Souls The Board Game,Painted World of Ariamis,Tomb of Giants,Executioner Chariot": [[14, 10, 7, 30, 5, 7, 7, 7], [9, 10, 7, 30, 27, 7, 7, 7], [14, 10, 7, 30, 27, 7, 7, 7], [10, 30, 7, 30, 27, 7, 7, 7], [14, 21, 7, 10, 30, 7, 7, 7], [14, 9, 7, 10, 30, 7, 7, 7], [14, 10, 7, 30, 30, 7, 7, 7], [21, 10, 7, 30, 27, 7, 7, 7], [10, 30, 7, 27, 27, 7, 7, 7], [14, 14, 7, 10, 30, 7, 7, 7], [10, 10, 7, 30, 27, 7, 7, 7], [14, 10, 7, 10, 30, 7, 7, 7]], "Dark Souls The Board Game,Painted World of Ariamis,Tomb of Giants,Explorers": [[21, 30, 7, 26, 27, 7, 7, 7], [30, 30, 7, 26, 27, 7, 7, 7], [9, 30, 7, 26, 27, 7, 7, 7], [14, 30, 7, 26, 27, 7, 7, 7], [14, 21, 7, 30, 26, 7, 7, 7], [14, 9, 7, 30, 26, 7, 7, 7], [14, 14, 7, 30, 26, 7, 7, 7], [14, 30, 7, 30, 26, 7, 7, 7], [14, 30, 7, 26, 26, 7, 7, 7]], "Dark Souls The Board Game,Explorers,Executioner Chariot,Painted World of Ariamis,Tomb of Giants": [[14, 10, 7, 30, 26, 7, 7, 7], [10, 30, 7, 26, 27, 7, 7, 7]], "Painted World of Ariamis,Tomb of Giants,Darkroot": [[21, 9, 7, 30, 22, 7, 7, 7], [30, 24, 7, 22, 22, 7, 7, 7], [30, 8, 7, 24, 24, 7, 7, 7], [21, 21, 7, 30, 24, 7, 7, 7], [9, 30, 7, 8, 22, 7, 7, 7], [21, 21, 7, 30, 22, 7, 7, 7], [21, 30, 7, 8, 24, 7, 7, 7], [21, 30, 7, 24, 22, 7, 7, 7], [9, 30, 7, 8, 5, 7, 7, 7], [21, 30, 7, 22, 22, 7, 7, 7], [30, 30, 7, 8, 24, 7, 7, 7], [9, 30, 7, 24, 22, 7, 7, 7], [30, 30, 7, 24, 5, 7, 7, 7], [30, 30, 7, 8, 22, 7, 7, 7], [21, 30, 7, 24, 24, 7, 7, 7], [30, 30, 7, 30, 8, 7, 7, 7], [30, 24, 7, 24, 22, 7, 7, 7], [21, 30, 7, 30, 22, 7, 7, 7], [21, 30, 7, 8, 22, 7, 7, 7], [9, 30, 7, 22, 22, 7, 7, 7], [30, 8, 7, 22, 5, 7, 7, 7], [30, 30, 7, 8, 5, 7, 7, 7], [21, 21, 7, 30, 8, 7, 7, 7], [21, 9, 7, 30, 8, 7, 7, 7], [21, 30, 7, 22, 5, 7, 7, 7], [30, 30, 7, 24, 24, 7, 7, 7], [30, 8, 7, 24, 22, 7, 7, 7], [9, 30, 7, 24, 24, 7, 7, 7], [9, 30, 7, 24, 5, 7, 7, 7], [9, 30, 7, 22, 5, 7, 7, 7], [9, 9, 7, 30, 24, 7, 7, 7], [30, 30, 7, 22, 5, 7, 7, 7], [30, 8, 7, 22, 22, 7, 7, 7], [30, 30, 7, 8, 8, 7, 7, 7], [9, 30, 7, 30, 8, 7, 7, 7], [21, 30, 7, 30, 8, 7, 7, 7], [21, 9, 7, 30, 24, 7, 7, 7], [21, 30, 7, 24, 5, 7, 7, 7], [30, 8, 7, 8, 24, 7, 7, 7], [30, 24, 7, 22, 5, 7, 7, 7], [30, 30, 7, 24, 22, 7, 7, 7], [9, 30, 7, 30, 24, 7, 7, 7], [21, 30, 7, 8, 5, 7, 7, 7], [21, 30, 7, 30, 24, 7, 7, 7], [21, 30, 7, 8, 8, 7, 7, 7], [30, 24, 7, 24, 24, 7, 7, 7], [9, 9, 7, 30, 22, 7, 7, 7], [9, 30, 7, 8, 24, 7, 7, 7], [30, 8, 7, 8, 22, 7, 7, 7], [9, 30, 7, 30, 22, 7, 7, 7], [30, 24, 7, 24, 5, 7, 7, 7], [30, 8, 7, 24, 5, 7, 7, 7], [9, 9, 7, 30, 8, 7, 7, 7], [9, 30, 7, 8, 8, 7, 7, 7]], "Executioner Chariot,Tomb of Giants,Darkroot,Painted World of Ariamis": [[9, 10, 7, 30, 22, 7, 7, 7], [10, 30, 7, 24, 5, 7, 7, 7], [9, 10, 7, 30, 24, 7, 7, 7], [10, 30, 7, 8, 24, 7, 7, 7], [21, 10, 7, 30, 24, 7, 7, 7], [21, 10, 7, 30, 22, 7, 7, 7], [21, 10, 7, 30, 8, 7, 7, 7], [10, 30, 7, 8, 5, 7, 7, 7], [10, 10, 7, 30, 22, 7, 7, 7], [10, 30, 7, 8, 22, 7, 7, 7], [10, 30, 7, 30, 22, 7, 7, 7], [10, 10, 7, 30, 24, 7, 7, 7], [10, 30, 7, 22, 22, 7, 7, 7], [10, 30, 7, 22, 5, 7, 7, 7], [10, 30, 7, 30, 24, 7, 7, 7], [10, 30, 7, 8, 8, 7, 7, 7], [10, 30, 7, 24, 22, 7, 7, 7], [10, 10, 7, 30, 8, 7, 7, 7], [10, 30, 7, 30, 8, 7, 7, 7], [10, 30, 7, 24, 24, 7, 7, 7], [9, 10, 7, 30, 8, 7, 7, 7]], "Explorers,Tomb of Giants,Darkroot,Painted World of Ariamis": [[30, 30, 7, 22, 26, 7, 7, 7], [30, 8, 7, 26, 26, 7, 7, 7], [9, 30, 7, 8, 26, 7, 7, 7], [21, 30, 7, 8, 26, 7, 7, 7], [30, 8, 7, 24, 26, 7, 7, 7], [21, 30, 7, 24, 26, 7, 7, 7], [30, 22, 7, 26, 26, 7, 7, 7], [21, 30, 7, 22, 26, 7, 7, 7], [9, 30, 7, 22, 26, 7, 7, 7], [30, 8, 7, 22, 26, 7, 7, 7], [30, 30, 7, 24, 26, 7, 7, 7], [30, 30, 7, 8, 26, 7, 7, 7], [30, 24, 7, 26, 26, 7, 7, 7], [30, 22, 7, 22, 26, 7, 7, 7], [30, 24, 7, 22, 26, 7, 7, 7], [9, 30, 7, 24, 26, 7, 7, 7], [30, 8, 7, 8, 26, 7, 7, 7], [30, 24, 7, 24, 26, 7, 7, 7]], "Explorers,Executioner Chariot,Painted World of Ariamis,Tomb of Giants,Darkroot": [[10, 30, 7, 24, 26, 7, 7, 7], [10, 30, 7, 8, 26, 7, 7, 7], [10, 30, 7, 22, 26, 7, 7, 7]], "Painted World of Ariamis,Tomb of Giants": [[21, 21, 7, 30, 5, 7, 7, 7], [21, 30, 7, 30, 5, 7, 7, 7], [21, 21, 7, 30, 30, 7, 7, 7], [21, 9, 7, 30, 30, 7, 7, 7], [9, 30, 7, 30, 5, 7, 7, 7], [21, 9, 7, 30, 5, 7, 7, 7], [30, 30, 7, 30, 5, 7, 7, 7], [21, 21, 7, 9, 30, 7, 7, 7], [9, 9, 7, 30, 5, 7, 7, 7], [21, 9, 7, 9, 30, 7, 7, 7], [9, 9, 7, 30, 30, 7, 7, 7], [9, 30, 7, 30, 30, 7, 7, 7], [21, 30, 7, 30, 30, 7, 7, 7], [21, 21, 7, 21, 30, 7, 7, 7]], "Painted World of Ariamis,Tomb of Giants,Executioner Chariot": [[9, 10, 7, 30, 5, 7, 7, 7], [9, 9, 7, 10, 30, 7, 7, 7], [9, 10, 7, 10, 30, 7, 7, 7], [21, 9, 7, 10, 30, 7, 7, 7], [9, 10, 7, 30, 30, 7, 7, 7], [10, 10, 7, 30, 5, 7, 7, 7], [21, 21, 7, 10, 30, 7, 7, 7], [21, 10, 7, 30, 5, 7, 7, 7], [21, 10, 7, 10, 30, 7, 7, 7], [10, 30, 7, 30, 5, 7, 7, 7], [10, 10, 7, 30, 30, 7, 7, 7], [10, 30, 7, 30, 30, 7, 7, 7], [21, 10, 7, 30, 30, 7, 7, 7]], "Explorers,Painted World of Ariamis,Tomb of Giants": [[21, 30, 7, 26, 26, 7, 7, 7], [9, 30, 7, 30, 26, 7, 7, 7], [21, 21, 7, 30, 26, 7, 7, 7], [9, 9, 7, 30, 26, 7, 7, 7], [21, 9, 7, 30, 26, 7, 7, 7], [30, 30, 7, 26, 26, 7, 7, 7], [21, 30, 7, 30, 26, 7, 7, 7], [9, 30, 7, 26, 26, 7, 7, 7], [30, 30, 7, 30, 26, 7, 7, 7]], "Explorers,Painted World of Ariamis,Tomb of Giants,Executioner Chariot": [[21, 10, 7, 30, 26, 7, 7, 7], [9, 10, 7, 30, 26, 7, 7, 7], [10, 30, 7, 26, 26, 7, 7, 7], [10, 10, 7, 30, 26, 7, 7, 7], [10, 30, 7, 30, 26, 7, 7, 7]], "Dark Souls The Board Game,Painted World of Ariamis,Iron Keep,Darkroot": [[8, 22, 7, 3, 27, 7, 7, 7], [21, 24, 7, 3, 27, 7, 7, 7], [14, 22, 7, 3, 27, 7, 7, 7], [8, 24, 7, 3, 27, 7, 7, 7], [14, 9, 7, 22, 3, 7, 7, 7], [14, 24, 7, 3, 27, 7, 7, 7], [14, 22, 7, 3, 5, 7, 7, 7], [14, 24, 7, 22, 3, 7, 7, 7], [22, 3, 7, 3, 27, 7, 7, 7], [9, 8, 7, 3, 27, 7, 7, 7], [14, 8, 7, 8, 3, 7, 7, 7], [14, 24, 7, 3, 3, 7, 7, 7], [14, 21, 7, 24, 3, 7, 7, 7], [14, 9, 7, 8, 3, 7, 7, 7], [14, 8, 7, 3, 27, 7, 7, 7], [14, 14, 7, 8, 3, 7, 7, 7], [14, 21, 7, 8, 3, 7, 7, 7], [14, 8, 7, 24, 3, 7, 7, 7], [14, 9, 7, 24, 3, 7, 7, 7], [8, 3, 7, 27, 27, 7, 7, 7], [8, 8, 7, 3, 27, 7, 7, 7], [21, 22, 7, 3, 27, 7, 7, 7], [14, 14, 7, 24, 3, 7, 7, 7], [14, 24, 7, 3, 5, 7, 7, 7], [24, 22, 7, 3, 27, 7, 7, 7], [24, 3, 7, 3, 27, 7, 7, 7], [22, 22, 7, 3, 27, 7, 7, 7], [14, 24, 7, 24, 3, 7, 7, 7], [21, 8, 7, 3, 27, 7, 7, 7], [24, 24, 7, 3, 27, 7, 7, 7], [8, 3, 7, 3, 27, 7, 7, 7], [14, 22, 7, 3, 3, 7, 7, 7], [14, 8, 7, 22, 3, 7, 7, 7], [14, 8, 7, 3, 5, 7, 7, 7], [14, 22, 7, 22, 3, 7, 7, 7], [9, 24, 7, 3, 27, 7, 7, 7], [14, 14, 7, 22, 3, 7, 7, 7], [9, 22, 7, 3, 27, 7, 7, 7], [14, 8, 7, 3, 3, 7, 7, 7], [14, 21, 7, 22, 3, 7, 7, 7]], "Dark Souls The Board Game,Executioner Chariot,Iron Keep,Painted World of Ariamis,Darkroot": [[14, 10, 7, 24, 3, 7, 7, 7], [10, 22, 7, 3, 27, 7, 7, 7], [10, 24, 7, 3, 27, 7, 7, 7], [10, 8, 7, 3, 27, 7, 7, 7], [14, 10, 7, 22, 3, 7, 7, 7], [14, 10, 7, 8, 3, 7, 7, 7]], "Dark Souls The Board Game,Explorers,Iron Keep,Painted World of Ariamis,Darkroot": [[24, 3, 7, 26, 27, 7, 7, 7], [14, 24, 7, 3, 26, 7, 7, 7], [14, 8, 7, 3, 26, 7, 7, 7], [14, 22, 7, 3, 26, 7, 7, 7], [22, 3, 7, 26, 27, 7, 7, 7], [8, 3, 7, 26, 27, 7, 7, 7]], "Dark Souls The Board Game,Painted World of Ariamis,Iron Keep": [[14, 9, 7, 3, 5, 7, 7, 7], [14, 21, 7, 3, 5, 7, 7, 7], [14, 21, 7, 3, 27, 7, 7, 7], [14, 14, 7, 3, 5, 7, 7, 7], [14, 3, 7, 27, 27, 7, 7, 7], [9, 3, 7, 27, 27, 7, 7, 7], [21, 9, 7, 3, 27, 7, 7, 7], [14, 9, 7, 3, 27, 7, 7, 7], [14, 9, 7, 3, 3, 7, 7, 7], [14, 14, 7, 3, 27, 7, 7, 7], [14, 21, 7, 21, 3, 7, 7, 7], [21, 3, 7, 27, 27, 7, 7, 7], [21, 21, 7, 3, 27, 7, 7, 7], [14, 21, 7, 3, 3, 7, 7, 7], [14, 14, 7, 21, 3, 7, 7, 7], [9, 3, 7, 3, 27, 7, 7, 7], [14, 21, 7, 9, 3, 7, 7, 7], [9, 9, 7, 3, 27, 7, 7, 7], [14, 3, 7, 3, 27, 7, 7, 7], [21, 3, 7, 3, 27, 7, 7, 7], [3, 3, 7, 3, 27, 7, 7, 7], [14, 14, 7, 3, 3, 7, 7, 7], [14, 3, 7, 3, 5, 7, 7, 7], [14, 3, 7, 3, 3, 7, 7, 7], [14, 9, 7, 9, 3, 7, 7, 7], [14, 14, 7, 9, 3, 7, 7, 7], [14, 14, 7, 14, 3, 7, 7, 7]], "Dark Souls The Board Game,Painted World of Ariamis,Iron Keep,Executioner Chariot": [[14, 10, 7, 3, 27, 7, 7, 7], [10, 10, 7, 3, 27, 7, 7, 7], [14, 21, 7, 10, 3, 7, 7, 7], [9, 10, 7, 3, 27, 7, 7, 7], [14, 10, 7, 3, 5, 7, 7, 7], [14, 14, 7, 10, 3, 7, 7, 7], [14, 10, 7, 10, 3, 7, 7, 7], [21, 10, 7, 3, 27, 7, 7, 7], [14, 9, 7, 10, 3, 7, 7, 7], [14, 10, 7, 3, 3, 7, 7, 7], [10, 3, 7, 27, 27, 7, 7, 7], [10, 3, 7, 3, 27, 7, 7, 7]], "Dark Souls The Board Game,Painted World of Ariamis,Iron Keep,Explorers": [[21, 3, 7, 26, 27, 7, 7, 7], [14, 14, 7, 3, 26, 7, 7, 7], [3, 3, 7, 26, 27, 7, 7, 7], [14, 9, 7, 3, 26, 7, 7, 7], [14, 3, 7, 26, 26, 7, 7, 7], [9, 3, 7, 26, 27, 7, 7, 7], [14, 3, 7, 26, 27, 7, 7, 7], [14, 3, 7, 3, 26, 7, 7, 7], [14, 21, 7, 3, 26, 7, 7, 7]], "Dark Souls The Board Game,Explorers,Executioner Chariot,Iron Keep,Painted World of Ariamis": [[10, 3, 7, 26, 27, 7, 7, 7], [14, 10, 7, 3, 26, 7, 7, 7]], "Painted World of Ariamis,Iron Keep,Darkroot": [[21, 21, 7, 22, 3, 7, 7, 7], [21, 22, 7, 3, 5, 7, 7, 7], [22, 22, 7, 22, 3, 7, 7, 7], [8, 8, 7, 3, 5, 7, 7, 7], [22, 3, 7, 3, 5, 7, 7, 7], [9, 24, 7, 24, 3, 7, 7, 7], [9, 22, 7, 22, 3, 7, 7, 7], [22, 22, 7, 3, 5, 7, 7, 7], [8, 24, 7, 22, 3, 7, 7, 7], [21, 8, 7, 22, 3, 7, 7, 7], [9, 9, 7, 22, 3, 7, 7, 7], [9, 24, 7, 22, 3, 7, 7, 7], [21, 21, 7, 24, 3, 7, 7, 7], [24, 3, 7, 3, 5, 7, 7, 7], [9, 22, 7, 3, 5, 7, 7, 7], [8, 8, 7, 24, 3, 7, 7, 7], [21, 9, 7, 8, 3, 7, 7, 7], [9, 24, 7, 3, 3, 7, 7, 7], [21, 8, 7, 24, 3, 7, 7, 7], [21, 8, 7, 3, 5, 7, 7, 7], [24, 22, 7, 22, 3, 7, 7, 7], [9, 8, 7, 3, 5, 7, 7, 7], [21, 9, 7, 22, 3, 7, 7, 7], [8, 8, 7, 22, 3, 7, 7, 7], [21, 24, 7, 22, 3, 7, 7, 7], [21, 24, 7, 24, 3, 7, 7, 7], [21, 24, 7, 3, 5, 7, 7, 7], [9, 9, 7, 24, 3, 7, 7, 7], [22, 22, 7, 3, 3, 7, 7, 7], [8, 24, 7, 24, 3, 7, 7, 7], [24, 24, 7, 3, 3, 7, 7, 7], [9, 8, 7, 24, 3, 7, 7, 7], [24, 24, 7, 24, 3, 7, 7, 7], [21, 21, 7, 8, 3, 7, 7, 7], [8, 22, 7, 3, 5, 7, 7, 7], [21, 8, 7, 3, 3, 7, 7, 7], [8, 24, 7, 3, 3, 7, 7, 7], [22, 3, 7, 3, 3, 7, 7, 7], [21, 24, 7, 3, 3, 7, 7, 7], [24, 22, 7, 3, 3, 7, 7, 7], [21, 9, 7, 24, 3, 7, 7, 7], [8, 22, 7, 3, 3, 7, 7, 7], [8, 3, 7, 3, 5, 7, 7, 7], [9, 8, 7, 22, 3, 7, 7, 7], [21, 22, 7, 3, 3, 7, 7, 7], [8, 22, 7, 22, 3, 7, 7, 7], [21, 22, 7, 22, 3, 7, 7, 7], [8, 24, 7, 3, 5, 7, 7, 7], [8, 8, 7, 3, 3, 7, 7, 7], [21, 8, 7, 8, 3, 7, 7, 7], [9, 8, 7, 3, 3, 7, 7, 7], [9, 9, 7, 8, 3, 7, 7, 7], [9, 8, 7, 8, 3, 7, 7, 7], [24, 22, 7, 3, 5, 7, 7, 7], [9, 22, 7, 3, 3, 7, 7, 7], [9, 24, 7, 3, 5, 7, 7, 7]], "Executioner Chariot,Iron Keep,Darkroot,Painted World of Ariamis": [[10, 24, 7, 22, 3, 7, 7, 7], [9, 10, 7, 24, 3, 7, 7, 7], [21, 10, 7, 24, 3, 7, 7, 7], [10, 8, 7, 24, 3, 7, 7, 7], [10, 10, 7, 8, 3, 7, 7, 7], [10, 8, 7, 8, 3, 7, 7, 7], [10, 8, 7, 3, 5, 7, 7, 7], [10, 24, 7, 3, 5, 7, 7, 7], [10, 22, 7, 22, 3, 7, 7, 7], [10, 10, 7, 22, 3, 7, 7, 7], [21, 10, 7, 8, 3, 7, 7, 7], [10, 24, 7, 3, 3, 7, 7, 7], [9, 10, 7, 8, 3, 7, 7, 7], [10, 10, 7, 24, 3, 7, 7, 7], [10, 8, 7, 22, 3, 7, 7, 7], [9, 10, 7, 22, 3, 7, 7, 7], [10, 8, 7, 3, 3, 7, 7, 7], [21, 10, 7, 22, 3, 7, 7, 7], [10, 22, 7, 3, 5, 7, 7, 7], [10, 24, 7, 24, 3, 7, 7, 7], [10, 22, 7, 3, 3, 7, 7, 7]], "Explorers,Iron Keep,Darkroot,Painted World of Ariamis": [[24, 24, 7, 3, 26, 7, 7, 7], [8, 3, 7, 26, 26, 7, 7, 7], [8, 24, 7, 3, 26, 7, 7, 7], [21, 8, 7, 3, 26, 7, 7, 7], [21, 22, 7, 3, 26, 7, 7, 7], [24, 3, 7, 26, 26, 7, 7, 7], [8, 22, 7, 3, 26, 7, 7, 7], [21, 24, 7, 3, 26, 7, 7, 7], [8, 8, 7, 3, 26, 7, 7, 7], [9, 8, 7, 3, 26, 7, 7, 7], [24, 22, 7, 3, 26, 7, 7, 7], [22, 3, 7, 26, 26, 7, 7, 7], [8, 3, 7, 3, 26, 7, 7, 7], [9, 24, 7, 3, 26, 7, 7, 7], [22, 3, 7, 3, 26, 7, 7, 7], [22, 22, 7, 3, 26, 7, 7, 7], [9, 22, 7, 3, 26, 7, 7, 7], [24, 3, 7, 3, 26, 7, 7, 7]], "Explorers,Executioner Chariot,Iron Keep,Painted World of Ariamis,Darkroot": [[10, 24, 7, 3, 26, 7, 7, 7], [10, 22, 7, 3, 26, 7, 7, 7], [10, 8, 7, 3, 26, 7, 7, 7]], "Painted World of Ariamis,Iron Keep": [[21, 9, 7, 3, 3, 7, 7, 7], [21, 3, 7, 3, 5, 7, 7, 7], [21, 9, 7, 3, 5, 7, 7, 7], [21, 21, 7, 3, 5, 7, 7, 7], [9, 3, 7, 3, 5, 7, 7, 7], [21, 9, 7, 9, 3, 7, 7, 7], [21, 21, 7, 3, 3, 7, 7, 7], [21, 21, 7, 9, 3, 7, 7, 7], [21, 21, 7, 21, 3, 7, 7, 7], [9, 9, 7, 3, 5, 7, 7, 7], [9, 3, 7, 3, 3, 7, 7, 7], [9, 9, 7, 3, 3, 7, 7, 7], [21, 3, 7, 3, 3, 7, 7, 7], [3, 3, 7, 3, 5, 7, 7, 7]], "Painted World of Ariamis,Iron Keep,Executioner Chariot": [[21, 21, 7, 10, 3, 7, 7, 7], [9, 10, 7, 3, 5, 7, 7, 7], [21, 10, 7, 3, 5, 7, 7, 7], [10, 10, 7, 3, 5, 7, 7, 7], [21, 10, 7, 3, 3, 7, 7, 7], [10, 3, 7, 3, 5, 7, 7, 7], [21, 10, 7, 10, 3, 7, 7, 7], [21, 9, 7, 10, 3, 7, 7, 7], [9, 9, 7, 10, 3, 7, 7, 7], [10, 3, 7, 3, 3, 7, 7, 7], [10, 10, 7, 3, 3, 7, 7, 7], [9, 10, 7, 3, 3, 7, 7, 7], [9, 10, 7, 10, 3, 7, 7, 7]], "Explorers,Painted World of Ariamis,Iron Keep": [[21, 9, 7, 3, 26, 7, 7, 7], [21, 21, 7, 3, 26, 7, 7, 7], [21, 3, 7, 3, 26, 7, 7, 7], [9, 9, 7, 3, 26, 7, 7, 7], [9, 3, 7, 26, 26, 7, 7, 7], [21, 3, 7, 26, 26, 7, 7, 7], [9, 3, 7, 3, 26, 7, 7, 7], [3, 3, 7, 3, 26, 7, 7, 7], [3, 3, 7, 26, 26, 7, 7, 7]], "Explorers,Painted World of Ariamis,Iron Keep,Executioner Chariot": [[10, 10, 7, 3, 26, 7, 7, 7], [10, 3, 7, 26, 26, 7, 7, 7], [9, 10, 7, 3, 26, 7, 7, 7], [21, 10, 7, 3, 26, 7, 7, 7], [10, 3, 7, 3, 26, 7, 7, 7]], "Dark Souls The Board Game,Painted World of Ariamis,Darkroot": [[14, 8, 7, 22, 27, 7, 7, 7], [24, 22, 7, 22, 27, 7, 7, 7], [9, 24, 7, 22, 27, 7, 7, 7], [21, 21, 7, 24, 27, 7, 7, 7], [14, 9, 7, 8, 27, 7, 7, 7], [14, 14, 7, 21, 22, 7, 7, 7], [14, 21, 7, 22, 27, 7, 7, 7], [9, 9, 7, 8, 27, 7, 7, 7], [21, 24, 7, 22, 27, 7, 7, 7], [14, 22, 7, 27, 27, 7, 7, 7], [14, 22, 7, 22, 27, 7, 7, 7], [14, 21, 7, 21, 24, 7, 7, 7], [14, 22, 7, 22, 5, 7, 7, 7], [24, 24, 7, 22, 27, 7, 7, 7], [14, 21, 7, 9, 24, 7, 7, 7], [21, 22, 7, 22, 27, 7, 7, 7], [21, 24, 7, 27, 27, 7, 7, 7], [14, 21, 7, 9, 22, 7, 7, 7], [21, 8, 7, 24, 27, 7, 7, 7], [14, 24, 7, 22, 5, 7, 7, 7], [8, 22, 7, 27, 27, 7, 7, 7], [14, 8, 7, 22, 5, 7, 7, 7], [14, 8, 7, 24, 5, 7, 7, 7], [14, 9, 7, 24, 27, 7, 7, 7], [14, 14, 7, 9, 8, 7, 7, 7], [14, 21, 7, 8, 27, 7, 7, 7], [14, 21, 7, 8, 22, 7, 7, 7], [14, 8, 7, 22, 22, 7, 7, 7], [14, 21, 7, 8, 5, 7, 7, 7], [14, 9, 7, 9, 8, 7, 7, 7], [21, 9, 7, 8, 27, 7, 7, 7], [14, 21, 7, 24, 27, 7, 7, 7], [21, 9, 7, 22, 27, 7, 7, 7], [14, 21, 7, 21, 8, 7, 7, 7], [14, 24, 7, 24, 22, 7, 7, 7], [14, 21, 7, 22, 5, 7, 7, 7], [14, 24, 7, 22, 27, 7, 7, 7], [9, 8, 7, 22, 27, 7, 7, 7], [14, 9, 7, 8, 22, 7, 7, 7], [21, 21, 7, 22, 27, 7, 7, 7], [14, 21, 7, 9, 8, 7, 7, 7], [8, 22, 7, 22, 27, 7, 7, 7], [14, 14, 7, 8, 22, 7, 7, 7], [14, 14, 7, 8, 5, 7, 7, 7], [14, 14, 7, 8, 27, 7, 7, 7], [14, 21, 7, 24, 24, 7, 7, 7], [9, 9, 7, 24, 27, 7, 7, 7], [9, 22, 7, 27, 27, 7, 7, 7], [14, 9, 7, 9, 24, 7, 7, 7], [9, 8, 7, 8, 27, 7, 7, 7], [8, 24, 7, 27, 27, 7, 7, 7], [24, 24, 7, 27, 27, 7, 7, 7], [14, 9, 7, 8, 5, 7, 7, 7], [14, 8, 7, 24, 27, 7, 7, 7], [14, 14, 7, 24, 5, 7, 7, 7], [14, 24, 7, 22, 22, 7, 7, 7], [14, 9, 7, 22, 5, 7, 7, 7], [14, 9, 7, 24, 22, 7, 7, 7], [14, 21, 7, 8, 8, 7, 7, 7], [14, 9, 7, 24, 5, 7, 7, 7], [21, 21, 7, 8, 27, 7, 7, 7], [8, 8, 7, 24, 27, 7, 7, 7], [14, 21, 7, 24, 22, 7, 7, 7], [14, 14, 7, 22, 27, 7, 7, 7], [22, 22, 7, 22, 27, 7, 7, 7], [14, 8, 7, 27, 27, 7, 7, 7], [14, 21, 7, 22, 22, 7, 7, 7], [14, 9, 7, 22, 27, 7, 7, 7], [8, 8, 7, 22, 27, 7, 7, 7], [14, 21, 7, 21, 22, 7, 7, 7], [9, 9, 7, 22, 27, 7, 7, 7], [14, 14, 7, 9, 22, 7, 7, 7], [14, 24, 7, 24, 24, 7, 7, 7], [14, 14, 7, 21, 8, 7, 7, 7], [14, 14, 7, 24, 22, 7, 7, 7], [14, 8, 7, 8, 27, 7, 7, 7], [21, 8, 7, 22, 27, 7, 7, 7], [14, 21, 7, 8, 24, 7, 7, 7], [9, 8, 7, 27, 27, 7, 7, 7], [8, 24, 7, 22, 27, 7, 7, 7], [14, 14, 7, 24, 27, 7, 7, 7]], "Dark Souls The Board Game,Executioner Chariot,Darkroot,Painted World of Ariamis": [[14, 10, 7, 24, 5, 7, 7, 7], [14, 9, 7, 10, 22, 7, 7, 7], [14, 14, 7, 10, 22, 7, 7, 7], [14, 10, 7, 8, 8, 7, 7, 7], [14, 21, 7, 10, 22, 7, 7, 7], [14, 9, 7, 10, 24, 7, 7, 7], [14, 10, 7, 24, 27, 7, 7, 7], [14, 21, 7, 10, 24, 7, 7, 7], [21, 10, 7, 22, 27, 7, 7, 7], [14, 10, 7, 8, 22, 7, 7, 7], [10, 24, 7, 22, 27, 7, 7, 7], [10, 22, 7, 22, 27, 7, 7, 7], [10, 22, 7, 27, 27, 7, 7, 7], [21, 10, 7, 8, 27, 7, 7, 7], [21, 10, 7, 24, 27, 7, 7, 7], [14, 10, 7, 10, 24, 7, 7, 7], [14, 10, 7, 24, 22, 7, 7, 7], [10, 10, 7, 22, 27, 7, 7, 7], [14, 14, 7, 10, 24, 7, 7, 7], [10, 8, 7, 24, 27, 7, 7, 7], [14, 10, 7, 22, 27, 7, 7, 7], [9, 10, 7, 8, 27, 7, 7, 7], [10, 24, 7, 27, 27, 7, 7, 7], [10, 8, 7, 22, 27, 7, 7, 7], [14, 10, 7, 22, 5, 7, 7, 7], [14, 10, 7, 8, 27, 7, 7, 7], [14, 10, 7, 24, 24, 7, 7, 7], [10, 8, 7, 8, 27, 7, 7, 7], [10, 10, 7, 24, 27, 7, 7, 7], [14, 10, 7, 22, 22, 7, 7, 7], [14, 10, 7, 8, 24, 7, 7, 7], [9, 10, 7, 22, 27, 7, 7, 7], [14, 10, 7, 8, 5, 7, 7, 7], [14, 21, 7, 10, 8, 7, 7, 7], [10, 10, 7, 8, 27, 7, 7, 7], [14, 10, 7, 10, 22, 7, 7, 7], [14, 9, 7, 10, 8, 7, 7, 7], [14, 10, 7, 10, 8, 7, 7, 7], [10, 24, 7, 24, 27, 7, 7, 7], [14, 14, 7, 10, 8, 7, 7, 7], [10, 8, 7, 27, 27, 7, 7, 7]], "Dark Souls The Board Game,Explorers,Darkroot,Painted World of Ariamis": [[14, 14, 7, 8, 26, 7, 7, 7], [21, 24, 7, 26, 27, 7, 7, 7], [14, 24, 7, 26, 27, 7, 7, 7], [14, 9, 7, 8, 26, 7, 7, 7], [14, 8, 7, 26, 27, 7, 7, 7], [22, 22, 7, 26, 27, 7, 7, 7], [21, 22, 7, 26, 27, 7, 7, 7], [14, 22, 7, 26, 26, 7, 7, 7], [14, 21, 7, 22, 26, 7, 7, 7], [14, 9, 7, 24, 26, 7, 7, 7], [9, 22, 7, 26, 27, 7, 7, 7], [14, 8, 7, 22, 26, 7, 7, 7], [14, 9, 7, 22, 26, 7, 7, 7], [14, 14, 7, 22, 26, 7, 7, 7], [14, 22, 7, 26, 27, 7, 7, 7], [14, 24, 7, 22, 26, 7, 7, 7], [24, 24, 7, 26, 27, 7, 7, 7], [14, 21, 7, 8, 26, 7, 7, 7], [21, 8, 7, 26, 27, 7, 7, 7], [14, 8, 7, 24, 26, 7, 7, 7], [14, 8, 7, 26, 26, 7, 7, 7], [8, 22, 7, 26, 27, 7, 7, 7], [14, 21, 7, 24, 26, 7, 7, 7], [24, 22, 7, 26, 27, 7, 7, 7], [9, 8, 7, 26, 27, 7, 7, 7], [14, 24, 7, 26, 26, 7, 7, 7], [14, 22, 7, 22, 26, 7, 7, 7], [9, 24, 7, 26, 27, 7, 7, 7], [14, 8, 7, 8, 26, 7, 7, 7], [14, 24, 7, 24, 26, 7, 7, 7], [14, 14, 7, 24, 26, 7, 7, 7], [8, 8, 7, 26, 27, 7, 7, 7], [8, 24, 7, 26, 27, 7, 7, 7]], "Dark Souls The Board Game,Explorers,Executioner Chariot,Painted World of Ariamis,Darkroot": [[14, 10, 7, 24, 26, 7, 7, 7], [10, 24, 7, 26, 27, 7, 7, 7], [14, 10, 7, 22, 26, 7, 7, 7], [10, 22, 7, 26, 27, 7, 7, 7], [14, 10, 7, 8, 26, 7, 7, 7], [10, 8, 7, 26, 27, 7, 7, 7]], "Dark Souls The Board Game,Painted World of Ariamis": [[14, 14, 7, 21, 9, 7, 7, 7], [21, 21, 7, 21, 27, 7, 7, 7], [14, 21, 7, 21, 9, 7, 7, 7], [14, 21, 7, 27, 5, 7, 7, 7], [14, 14, 7, 21, 21, 7, 7, 7], [14, 14, 7, 9, 27, 7, 7, 7], [14, 21, 7, 9, 9, 7, 7, 7], [14, 14, 7, 9, 5, 7, 7, 7], [14, 21, 7, 21, 21, 7, 7, 7], [14, 14, 7, 21, 27, 7, 7, 7], [21, 9, 7, 27, 5, 7, 7, 7], [14, 21, 7, 21, 5, 7, 7, 7], [14, 21, 7, 21, 27, 7, 7, 7], [14, 21, 7, 9, 5, 7, 7, 7], [14, 14, 7, 14, 9, 7, 7, 7], [9, 9, 7, 27, 5, 7, 7, 7], [14, 9, 7, 27, 27, 7, 7, 7], [14, 21, 7, 27, 27, 7, 7, 7], [21, 9, 7, 27, 27, 7, 7, 7], [21, 21, 7, 27, 5, 7, 7, 7], [14, 21, 7, 9, 27, 7, 7, 7], [14, 9, 7, 9, 27, 7, 7, 7], [21, 21, 7, 9, 27, 7, 7, 7], [14, 14, 7, 21, 5, 7, 7, 7], [14, 14, 7, 27, 5, 7, 7, 7], [14, 14, 7, 27, 27, 7, 7, 7], [21, 21, 7, 27, 27, 7, 7, 7], [14, 9, 7, 9, 5, 7, 7, 7], [21, 9, 7, 9, 27, 7, 7, 7], [14, 14, 7, 14, 21, 7, 7, 7], [14, 14, 7, 9, 9, 7, 7, 7], [14, 9, 7, 27, 5, 7, 7, 7], [14, 14, 7, 14, 27, 7, 7, 7]], "Dark Souls The Board Game,Painted World of Ariamis,Executioner Chariot": [[14, 14, 7, 21, 10, 7, 7, 7], [21, 10, 7, 27, 27, 7, 7, 7], [21, 9, 7, 10, 27, 7, 7, 7], [14, 9, 7, 9, 10, 7, 7, 7], [14, 21, 7, 9, 10, 7, 7, 7], [9, 10, 7, 27, 27, 7, 7, 7], [14, 21, 7, 10, 27, 7, 7, 7], [14, 14, 7, 10, 5, 7, 7, 7], [14, 10, 7, 10, 27, 7, 7, 7], [14, 9, 7, 10, 27, 7, 7, 7], [14, 10, 7, 27, 5, 7, 7, 7], [14, 14, 7, 14, 10, 7, 7, 7], [14, 21, 7, 10, 5, 7, 7, 7], [14, 10, 7, 10, 5, 7, 7, 7], [14, 21, 7, 21, 10, 7, 7, 7], [14, 9, 7, 10, 10, 7, 7, 7], [14, 10, 7, 27, 27, 7, 7, 7], [14, 14, 7, 9, 10, 7, 7, 7], [14, 9, 7, 10, 5, 7, 7, 7], [21, 10, 7, 10, 27, 7, 7, 7], [14, 21, 7, 10, 10, 7, 7, 7], [14, 14, 7, 10, 27, 7, 7, 7], [21, 21, 7, 10, 27, 7, 7, 7], [14, 14, 7, 10, 10, 7, 7, 7], [9, 10, 7, 10, 27, 7, 7, 7], [9, 9, 7, 10, 27, 7, 7, 7], [10, 10, 7, 27, 27, 7, 7, 7]], "Dark Souls The Board Game,Painted World of Ariamis,Explorers": [[21, 21, 7, 26, 27, 7, 7, 7], [14, 9, 7, 26, 5, 7, 7, 7], [14, 9, 7, 9, 26, 7, 7, 7], [14, 21, 7, 26, 27, 7, 7, 7], [14, 14, 7, 9, 26, 7, 7, 7], [14, 21, 7, 9, 26, 7, 7, 7], [14, 9, 7, 26, 27, 7, 7, 7], [14, 14, 7, 26, 27, 7, 7, 7], [14, 14, 7, 26, 26, 7, 7, 7], [14, 9, 7, 26, 26, 7, 7, 7], [14, 21, 7, 21, 26, 7, 7, 7], [14, 14, 7, 21, 26, 7, 7, 7], [21, 9, 7, 26, 27, 7, 7, 7], [14, 21, 7, 26, 5, 7, 7, 7], [14, 14, 7, 26, 5, 7, 7, 7], [9, 9, 7, 26, 27, 7, 7, 7], [14, 14, 7, 14, 26, 7, 7, 7], [14, 21, 7, 26, 26, 7, 7, 7]], "Dark Souls The Board Game,Painted World of Ariamis,Explorers,Executioner Chariot": [[14, 14, 7, 10, 26, 7, 7, 7], [14, 10, 7, 10, 26, 7, 7, 7], [14, 10, 7, 26, 27, 7, 7, 7], [10, 10, 7, 26, 27, 7, 7, 7], [21, 10, 7, 26, 27, 7, 7, 7], [14, 9, 7, 10, 26, 7, 7, 7], [14, 10, 7, 26, 5, 7, 7, 7], [14, 10, 7, 26, 26, 7, 7, 7], [14, 21, 7, 10, 26, 7, 7, 7], [9, 10, 7, 26, 27, 7, 7, 7]], "Painted World of Ariamis,Darkroot": [[9, 24, 7, 24, 5, 7, 7, 7], [21, 21, 7, 9, 22, 7, 7, 7], [9, 8, 7, 24, 22, 7, 7, 7], [9, 24, 7, 24, 22, 7, 7, 7], [9, 9, 7, 24, 5, 7, 7, 7], [9, 24, 7, 22, 5, 7, 7, 7], [21, 21, 7, 8, 24, 7, 7, 7], [21, 9, 7, 24, 22, 7, 7, 7], [8, 24, 7, 24, 24, 7, 7, 7], [8, 8, 7, 22, 22, 7, 7, 7], [21, 8, 7, 24, 22, 7, 7, 7], [21, 9, 7, 8, 24, 7, 7, 7], [8, 24, 7, 24, 22, 7, 7, 7], [9, 8, 7, 22, 5, 7, 7, 7], [9, 22, 7, 22, 5, 7, 7, 7], [9, 9, 7, 8, 24, 7, 7, 7], [21, 9, 7, 24, 5, 7, 7, 7], [9, 24, 7, 22, 22, 7, 7, 7], [21, 21, 7, 24, 24, 7, 7, 7], [24, 24, 7, 22, 5, 7, 7, 7], [21, 8, 7, 22, 22, 7, 7, 7], [21, 24, 7, 24, 22, 7, 7, 7], [9, 9, 7, 8, 8, 7, 7, 7], [21, 21, 7, 9, 8, 7, 7, 7], [8, 8, 7, 22, 5, 7, 7, 7], [21, 9, 7, 8, 5, 7, 7, 7], [21, 21, 7, 24, 5, 7, 7, 7], [8, 24, 7, 22, 22, 7, 7, 7], [21, 9, 7, 22, 5, 7, 7, 7], [21, 9, 7, 8, 8, 7, 7, 7], [9, 9, 7, 22, 5, 7, 7, 7], [9, 8, 7, 22, 22, 7, 7, 7], [8, 22, 7, 22, 5, 7, 7, 7], [21, 24, 7, 22, 5, 7, 7, 7], [21, 21, 7, 8, 22, 7, 7, 7], [21, 21, 7, 9, 24, 7, 7, 7], [21, 21, 7, 22, 5, 7, 7, 7], [21, 8, 7, 22, 5, 7, 7, 7], [21, 8, 7, 8, 5, 7, 7, 7], [21, 21, 7, 24, 22, 7, 7, 7], [21, 8, 7, 24, 5, 7, 7, 7], [8, 8, 7, 24, 5, 7, 7, 7], [21, 9, 7, 9, 8, 7, 7, 7], [9, 9, 7, 22, 22, 7, 7, 7], [8, 24, 7, 24, 5, 7, 7, 7], [9, 9, 7, 24, 24, 7, 7, 7], [8, 8, 7, 24, 22, 7, 7, 7], [8, 24, 7, 22, 5, 7, 7, 7], [21, 21, 7, 8, 5, 7, 7, 7], [21, 9, 7, 22, 22, 7, 7, 7], [9, 22, 7, 22, 22, 7, 7, 7], [24, 24, 7, 22, 22, 7, 7, 7], [9, 8, 7, 24, 5, 7, 7, 7], [21, 24, 7, 24, 5, 7, 7, 7], [21, 9, 7, 9, 24, 7, 7, 7], [21, 9, 7, 8, 22, 7, 7, 7], [24, 22, 7, 22, 22, 7, 7, 7], [21, 9, 7, 24, 24, 7, 7, 7], [21, 21, 7, 8, 8, 7, 7, 7], [9, 8, 7, 8, 24, 7, 7, 7], [21, 8, 7, 24, 24, 7, 7, 7], [21, 21, 7, 22, 22, 7, 7, 7], [24, 22, 7, 22, 5, 7, 7, 7], [21, 8, 7, 8, 24, 7, 7, 7], [9, 9, 7, 24, 22, 7, 7, 7], [21, 22, 7, 22, 22, 7, 7, 7], [21, 9, 7, 9, 22, 7, 7, 7], [9, 8, 7, 8, 22, 7, 7, 7], [21, 24, 7, 24, 24, 7, 7, 7]], "Painted World of Ariamis,Darkroot,Executioner Chariot": [[21, 10, 7, 24, 22, 7, 7, 7], [9, 10, 7, 24, 5, 7, 7, 7], [10, 8, 7, 22, 5, 7, 7, 7], [21, 10, 7, 24, 5, 7, 7, 7], [9, 10, 7, 24, 22, 7, 7, 7], [10, 24, 7, 24, 24, 7, 7, 7], [21, 10, 7, 22, 22, 7, 7, 7], [21, 9, 7, 10, 22, 7, 7, 7], [10, 8, 7, 8, 5, 7, 7, 7], [10, 10, 7, 22, 5, 7, 7, 7], [10, 24, 7, 22, 5, 7, 7, 7], [9, 10, 7, 8, 24, 7, 7, 7], [21, 21, 7, 10, 8, 7, 7, 7], [9, 10, 7, 10, 22, 7, 7, 7], [10, 10, 7, 8, 24, 7, 7, 7], [21, 9, 7, 10, 8, 7, 7, 7], [21, 9, 7, 10, 24, 7, 7, 7], [21, 21, 7, 10, 24, 7, 7, 7], [9, 10, 7, 22, 5, 7, 7, 7], [10, 10, 7, 24, 22, 7, 7, 7], [10, 24, 7, 24, 5, 7, 7, 7], [10, 22, 7, 22, 5, 7, 7, 7], [9, 10, 7, 10, 24, 7, 7, 7], [10, 24, 7, 22, 22, 7, 7, 7], [21, 10, 7, 22, 5, 7, 7, 7], [21, 10, 7, 8, 8, 7, 7, 7], [9, 10, 7, 8, 22, 7, 7, 7], [10, 8, 7, 24, 24, 7, 7, 7], [10, 8, 7, 8, 24, 7, 7, 7], [21, 10, 7, 24, 24, 7, 7, 7], [10, 24, 7, 24, 22, 7, 7, 7], [21, 10, 7, 8, 22, 7, 7, 7], [21, 10, 7, 10, 24, 7, 7, 7], [21, 21, 7, 10, 22, 7, 7, 7], [9, 10, 7, 24, 24, 7, 7, 7], [9, 9, 7, 10, 8, 7, 7, 7], [9, 10, 7, 22, 22, 7, 7, 7], [10, 8, 7, 24, 22, 7, 7, 7], [21, 10, 7, 8, 24, 7, 7, 7], [10, 8, 7, 22, 22, 7, 7, 7], [9, 9, 7, 10, 22, 7, 7, 7], [10, 10, 7, 24, 24, 7, 7, 7], [21, 10, 7, 10, 8, 7, 7, 7], [9, 10, 7, 8, 5, 7, 7, 7], [10, 10, 7, 8, 22, 7, 7, 7], [10, 8, 7, 24, 5, 7, 7, 7], [9, 10, 7, 10, 8, 7, 7, 7], [10, 8, 7, 8, 22, 7, 7, 7], [21, 10, 7, 8, 5, 7, 7, 7], [10, 10, 7, 22, 22, 7, 7, 7], [21, 10, 7, 10, 22, 7, 7, 7]], "Explorers,Painted World of Ariamis,Darkroot": [[21, 21, 7, 22, 26, 7, 7, 7], [21, 8, 7, 24, 26, 7, 7, 7], [21, 21, 7, 8, 26, 7, 7, 7], [9, 8, 7, 22, 26, 7, 7, 7], [21, 24, 7, 24, 26, 7, 7, 7], [21, 8, 7, 26, 26, 7, 7, 7], [8, 8, 7, 22, 26, 7, 7, 7], [8, 24, 7, 24, 26, 7, 7, 7], [21, 8, 7, 22, 26, 7, 7, 7], [21, 9, 7, 8, 26, 7, 7, 7], [9, 24, 7, 22, 26, 7, 7, 7], [21, 8, 7, 8, 26, 7, 7, 7], [21, 22, 7, 26, 26, 7, 7, 7], [21, 24, 7, 22, 26, 7, 7, 7], [8, 22, 7, 22, 26, 7, 7, 7], [8, 22, 7, 26, 26, 7, 7, 7], [9, 9, 7, 22, 26, 7, 7, 7], [9, 22, 7, 26, 26, 7, 7, 7], [9, 8, 7, 26, 26, 7, 7, 7], [22, 22, 7, 22, 26, 7, 7, 7], [21, 21, 7, 24, 26, 7, 7, 7], [24, 22, 7, 22, 26, 7, 7, 7], [8, 24, 7, 22, 26, 7, 7, 7], [21, 9, 7, 22, 26, 7, 7, 7], [21, 9, 7, 24, 26, 7, 7, 7], [8, 24, 7, 26, 26, 7, 7, 7], [9, 8, 7, 24, 26, 7, 7, 7], [21, 22, 7, 22, 26, 7, 7, 7], [9, 24, 7, 26, 26, 7, 7, 7], [21, 24, 7, 26, 26, 7, 7, 7], [9, 9, 7, 24, 26, 7, 7, 7], [24, 24, 7, 24, 26, 7, 7, 7], [9, 22, 7, 22, 26, 7, 7, 7], [9, 9, 7, 8, 26, 7, 7, 7], [24, 24, 7, 22, 26, 7, 7, 7], [22, 22, 7, 26, 26, 7, 7, 7], [24, 24, 7, 26, 26, 7, 7, 7], [8, 8, 7, 26, 26, 7, 7, 7], [9, 8, 7, 8, 26, 7, 7, 7], [9, 24, 7, 24, 26, 7, 7, 7]], "Explorers,Executioner Chariot,Darkroot,Painted World of Ariamis": [[10, 8, 7, 26, 26, 7, 7, 7], [21, 10, 7, 24, 26, 7, 7, 7], [21, 10, 7, 22, 26, 7, 7, 7], [9, 10, 7, 22, 26, 7, 7, 7], [10, 24, 7, 22, 26, 7, 7, 7], [10, 22, 7, 26, 26, 7, 7, 7], [9, 10, 7, 24, 26, 7, 7, 7], [10, 22, 7, 22, 26, 7, 7, 7], [9, 10, 7, 8, 26, 7, 7, 7], [10, 10, 7, 8, 26, 7, 7, 7], [10, 8, 7, 22, 26, 7, 7, 7], [10, 8, 7, 8, 26, 7, 7, 7], [10, 24, 7, 26, 26, 7, 7, 7], [10, 10, 7, 22, 26, 7, 7, 7], [10, 8, 7, 24, 26, 7, 7, 7], [21, 10, 7, 8, 26, 7, 7, 7], [10, 10, 7, 24, 26, 7, 7, 7], [10, 24, 7, 24, 26, 7, 7, 7]], "Painted World of Ariamis,Executioner Chariot": [[21, 21, 7, 10, 5, 7, 7, 7], [21, 9, 7, 9, 10, 7, 7, 7], [21, 9, 7, 10, 5, 7, 7, 7], [21, 21, 7, 9, 10, 7, 7, 7], [21, 10, 7, 10, 5, 7, 7, 7], [21, 9, 7, 10, 10, 7, 7, 7], [9, 10, 7, 10, 5, 7, 7, 7], [9, 9, 7, 10, 5, 7, 7, 7], [21, 21, 7, 10, 10, 7, 7, 7], [21, 21, 7, 21, 10, 7, 7, 7], [9, 9, 7, 10, 10, 7, 7, 7]], "Explorers,Painted World of Ariamis,Executioner Chariot": [[21, 9, 7, 10, 26, 7, 7, 7], [9, 10, 7, 26, 26, 7, 7, 7], [21, 10, 7, 10, 26, 7, 7, 7], [9, 9, 7, 10, 26, 7, 7, 7], [21, 21, 7, 10, 26, 7, 7, 7], [21, 10, 7, 26, 26, 7, 7, 7], [9, 10, 7, 26, 5, 7, 7, 7], [9, 10, 7, 10, 26, 7, 7, 7], [21, 10, 7, 26, 5, 7, 7, 7], [10, 10, 7, 26, 26, 7, 7, 7]], "Explorers,Painted World of Ariamis": [[21, 9, 7, 26, 5, 7, 7, 7], [21, 21, 7, 26, 5, 7, 7, 7], [21, 21, 7, 21, 26, 7, 7, 7], [9, 9, 7, 26, 5, 7, 7, 7], [21, 21, 7, 26, 26, 7, 7, 7], [21, 9, 7, 26, 26, 7, 7, 7], [21, 9, 7, 9, 26, 7, 7, 7], [21, 21, 7, 9, 26, 7, 7, 7], [9, 9, 7, 26, 26, 7, 7, 7]], "Painted World of Ariamis": [[21, 9, 7, 9, 5, 7, 7, 7], [21, 21, 7, 9, 5, 7, 7, 7], [21, 21, 7, 21, 9, 7, 7, 7], [21, 21, 7, 9, 9, 7, 7, 7], [21, 21, 7, 21, 5, 7, 7, 7], [21, 21, 7, 21, 21, 7, 7, 7]], "The Sunless City,Iron Keep,Painted World of Ariamis,Tomb of Giants,Darkroot": [[14, 30, 7, 22, 3, 7, 7, 7], [30, 22, 7, 3, 27, 7, 7, 7], [30, 24, 7, 3, 27, 7, 7, 7], [14, 30, 7, 8, 3, 7, 7, 7], [30, 8, 7, 3, 27, 7, 7, 7], [14, 30, 7, 24, 3, 7, 7, 7]], "The Sunless City,Painted World of Ariamis,Tomb of Giants,Iron Keep": [[21, 30, 7, 3, 27, 7, 7, 7], [14, 9, 7, 30, 3, 7, 7, 7], [14, 30, 7, 30, 3, 7, 7, 7], [14, 30, 7, 3, 3, 7, 7, 7], [14, 30, 7, 3, 5, 7, 7, 7], [14, 21, 7, 30, 3, 7, 7, 7], [9, 30, 7, 3, 27, 7, 7, 7], [14, 30, 7, 3, 27, 7, 7, 7], [14, 14, 7, 30, 3, 7, 7, 7], [30, 3, 7, 27, 27, 7, 7, 7], [30, 30, 7, 3, 27, 7, 7, 7], [30, 3, 7, 3, 27, 7, 7, 7]], "The Sunless City,Executioner Chariot,Iron Keep,Painted World of Ariamis,Tomb of Giants": [[10, 30, 7, 3, 27, 7, 7, 7], [14, 10, 7, 30, 3, 7, 7, 7]], "The Sunless City,Explorers,Iron Keep,Painted World of Ariamis,Tomb of Giants": [[14, 30, 7, 3, 26, 7, 7, 7], [30, 3, 7, 26, 27, 7, 7, 7]], "The Sunless City,Painted World of Ariamis,Tomb of Giants,Darkroot": [[14, 30, 7, 30, 24, 7, 7, 7], [14, 30, 7, 30, 8, 7, 7, 7], [9, 30, 7, 8, 27, 7, 7, 7], [14, 30, 7, 8, 22, 7, 7, 7], [30, 30, 7, 24, 27, 7, 7, 7], [14, 21, 7, 30, 24, 7, 7, 7], [14, 30, 7, 24, 22, 7, 7, 7], [9, 30, 7, 22, 27, 7, 7, 7], [14, 14, 7, 30, 22, 7, 7, 7], [14, 30, 7, 30, 22, 7, 7, 7], [14, 14, 7, 30, 24, 7, 7, 7], [21, 30, 7, 24, 27, 7, 7, 7], [14, 30, 7, 8, 27, 7, 7, 7], [14, 30, 7, 8, 24, 7, 7, 7], [30, 22, 7, 22, 27, 7, 7, 7], [14, 30, 7, 22, 27, 7, 7, 7], [14, 21, 7, 30, 22, 7, 7, 7], [30, 22, 7, 27, 27, 7, 7, 7], [14, 9, 7, 30, 8, 7, 7, 7], [30, 24, 7, 22, 27, 7, 7, 7], [21, 30, 7, 22, 27, 7, 7, 7], [14, 30, 7, 8, 5, 7, 7, 7], [14, 9, 7, 30, 22, 7, 7, 7], [14, 14, 7, 30, 8, 7, 7, 7], [14, 30, 7, 24, 24, 7, 7, 7], [14, 30, 7, 22, 22, 7, 7, 7], [30, 24, 7, 27, 27, 7, 7, 7], [30, 24, 7, 24, 27, 7, 7, 7], [14, 9, 7, 30, 24, 7, 7, 7], [14, 21, 7, 30, 8, 7, 7, 7], [9, 30, 7, 24, 27, 7, 7, 7], [30, 8, 7, 27, 27, 7, 7, 7], [21, 30, 7, 8, 27, 7, 7, 7], [14, 30, 7, 24, 5, 7, 7, 7], [30, 8, 7, 24, 27, 7, 7, 7], [30, 8, 7, 8, 27, 7, 7, 7], [30, 8, 7, 22, 27, 7, 7, 7], [14, 30, 7, 22, 5, 7, 7, 7], [30, 30, 7, 8, 27, 7, 7, 7], [14, 30, 7, 8, 8, 7, 7, 7], [14, 30, 7, 24, 27, 7, 7, 7]], "The Sunless City,Executioner Chariot,Painted World of Ariamis,Tomb of Giants,Darkroot": [[14, 10, 7, 30, 24, 7, 7, 7], [14, 10, 7, 30, 22, 7, 7, 7], [10, 30, 7, 24, 27, 7, 7, 7], [10, 30, 7, 8, 27, 7, 7, 7], [14, 10, 7, 30, 8, 7, 7, 7], [10, 30, 7, 22, 27, 7, 7, 7]], "The Sunless City,Explorers,Painted World of Ariamis,Tomb of Giants,Darkroot": [[14, 30, 7, 22, 26, 7, 7, 7], [30, 8, 7, 26, 27, 7, 7, 7], [30, 22, 7, 26, 27, 7, 7, 7], [14, 30, 7, 8, 26, 7, 7, 7], [30, 24, 7, 26, 27, 7, 7, 7], [14, 30, 7, 24, 26, 7, 7, 7]], "The Sunless City,Painted World of Ariamis,Tomb of Giants": [[14, 14, 7, 30, 30, 7, 7, 7], [14, 14, 7, 14, 30, 7, 7, 7], [14, 21, 7, 30, 27, 7, 7, 7], [21, 9, 7, 30, 27, 7, 7, 7], [14, 9, 7, 30, 5, 7, 7, 7], [14, 30, 7, 30, 30, 7, 7, 7], [14, 14, 7, 30, 5, 7, 7, 7], [14, 30, 7, 27, 27, 7, 7, 7], [14, 9, 7, 30, 27, 7, 7, 7], [14, 30, 7, 30, 5, 7, 7, 7], [21, 30, 7, 27, 27, 7, 7, 7], [14, 14, 7, 9, 30, 7, 7, 7], [14, 30, 7, 30, 27, 7, 7, 7], [30, 30, 7, 30, 27, 7, 7, 7], [9, 9, 7, 30, 27, 7, 7, 7], [14, 9, 7, 30, 30, 7, 7, 7], [14, 14, 7, 30, 27, 7, 7, 7], [21, 30, 7, 30, 27, 7, 7, 7], [14, 21, 7, 30, 30, 7, 7, 7], [14, 21, 7, 21, 30, 7, 7, 7], [14, 21, 7, 30, 5, 7, 7, 7], [9, 30, 7, 27, 27, 7, 7, 7], [14, 21, 7, 9, 30, 7, 7, 7], [9, 30, 7, 30, 27, 7, 7, 7], [30, 30, 7, 27, 27, 7, 7, 7], [14, 9, 7, 9, 30, 7, 7, 7], [14, 14, 7, 21, 30, 7, 7, 7], [21, 21, 7, 30, 27, 7, 7, 7]], "The Sunless City,Painted World of Ariamis,Tomb of Giants,Executioner Chariot": [[14, 10, 7, 30, 5, 7, 7, 7], [9, 10, 7, 30, 27, 7, 7, 7], [14, 10, 7, 30, 27, 7, 7, 7], [10, 30, 7, 30, 27, 7, 7, 7], [14, 21, 7, 10, 30, 7, 7, 7], [14, 9, 7, 10, 30, 7, 7, 7], [14, 10, 7, 30, 30, 7, 7, 7], [21, 10, 7, 30, 27, 7, 7, 7], [10, 30, 7, 27, 27, 7, 7, 7], [14, 14, 7, 10, 30, 7, 7, 7], [10, 10, 7, 30, 27, 7, 7, 7], [14, 10, 7, 10, 30, 7, 7, 7]], "The Sunless City,Painted World of Ariamis,Tomb of Giants,Explorers": [[21, 30, 7, 26, 27, 7, 7, 7], [30, 30, 7, 26, 27, 7, 7, 7], [9, 30, 7, 26, 27, 7, 7, 7], [14, 30, 7, 26, 27, 7, 7, 7], [14, 21, 7, 30, 26, 7, 7, 7], [14, 9, 7, 30, 26, 7, 7, 7], [14, 14, 7, 30, 26, 7, 7, 7], [14, 30, 7, 30, 26, 7, 7, 7], [14, 30, 7, 26, 26, 7, 7, 7]], "The Sunless City,Explorers,Executioner Chariot,Painted World of Ariamis,Tomb of Giants": [[14, 10, 7, 30, 26, 7, 7, 7], [10, 30, 7, 26, 27, 7, 7, 7]], "The Sunless City,Painted World of Ariamis,Iron Keep,Darkroot": [[8, 22, 7, 3, 27, 7, 7, 7], [21, 24, 7, 3, 27, 7, 7, 7], [14, 22, 7, 3, 27, 7, 7, 7], [8, 24, 7, 3, 27, 7, 7, 7], [14, 9, 7, 22, 3, 7, 7, 7], [14, 24, 7, 3, 27, 7, 7, 7], [14, 22, 7, 3, 5, 7, 7, 7], [14, 24, 7, 22, 3, 7, 7, 7], [22, 3, 7, 3, 27, 7, 7, 7], [9, 8, 7, 3, 27, 7, 7, 7], [14, 8, 7, 8, 3, 7, 7, 7], [14, 24, 7, 3, 3, 7, 7, 7], [14, 21, 7, 24, 3, 7, 7, 7], [14, 9, 7, 8, 3, 7, 7, 7], [14, 8, 7, 3, 27, 7, 7, 7], [14, 14, 7, 8, 3, 7, 7, 7], [14, 21, 7, 8, 3, 7, 7, 7], [14, 8, 7, 24, 3, 7, 7, 7], [14, 9, 7, 24, 3, 7, 7, 7], [8, 3, 7, 27, 27, 7, 7, 7], [8, 8, 7, 3, 27, 7, 7, 7], [21, 22, 7, 3, 27, 7, 7, 7], [14, 14, 7, 24, 3, 7, 7, 7], [14, 24, 7, 3, 5, 7, 7, 7], [24, 22, 7, 3, 27, 7, 7, 7], [24, 3, 7, 3, 27, 7, 7, 7], [22, 22, 7, 3, 27, 7, 7, 7], [14, 24, 7, 24, 3, 7, 7, 7], [21, 8, 7, 3, 27, 7, 7, 7], [24, 24, 7, 3, 27, 7, 7, 7], [8, 3, 7, 3, 27, 7, 7, 7], [14, 22, 7, 3, 3, 7, 7, 7], [14, 8, 7, 22, 3, 7, 7, 7], [14, 8, 7, 3, 5, 7, 7, 7], [14, 22, 7, 22, 3, 7, 7, 7], [9, 24, 7, 3, 27, 7, 7, 7], [14, 14, 7, 22, 3, 7, 7, 7], [9, 22, 7, 3, 27, 7, 7, 7], [14, 8, 7, 3, 3, 7, 7, 7], [14, 21, 7, 22, 3, 7, 7, 7]], "The Sunless City,Executioner Chariot,Iron Keep,Painted World of Ariamis,Darkroot": [[14, 10, 7, 24, 3, 7, 7, 7], [10, 22, 7, 3, 27, 7, 7, 7], [10, 24, 7, 3, 27, 7, 7, 7], [10, 8, 7, 3, 27, 7, 7, 7], [14, 10, 7, 22, 3, 7, 7, 7], [14, 10, 7, 8, 3, 7, 7, 7]], "The Sunless City,Explorers,Iron Keep,Painted World of Ariamis,Darkroot": [[24, 3, 7, 26, 27, 7, 7, 7], [14, 24, 7, 3, 26, 7, 7, 7], [14, 8, 7, 3, 26, 7, 7, 7], [14, 22, 7, 3, 26, 7, 7, 7], [22, 3, 7, 26, 27, 7, 7, 7], [8, 3, 7, 26, 27, 7, 7, 7]], "The Sunless City,Painted World of Ariamis,Iron Keep": [[14, 9, 7, 3, 5, 7, 7, 7], [14, 21, 7, 3, 5, 7, 7, 7], [14, 21, 7, 3, 27, 7, 7, 7], [14, 14, 7, 3, 5, 7, 7, 7], [14, 3, 7, 27, 27, 7, 7, 7], [9, 3, 7, 27, 27, 7, 7, 7], [21, 9, 7, 3, 27, 7, 7, 7], [14, 9, 7, 3, 27, 7, 7, 7], [14, 9, 7, 3, 3, 7, 7, 7], [14, 14, 7, 3, 27, 7, 7, 7], [14, 21, 7, 21, 3, 7, 7, 7], [21, 3, 7, 27, 27, 7, 7, 7], [21, 21, 7, 3, 27, 7, 7, 7], [14, 21, 7, 3, 3, 7, 7, 7], [14, 14, 7, 21, 3, 7, 7, 7], [9, 3, 7, 3, 27, 7, 7, 7], [14, 21, 7, 9, 3, 7, 7, 7], [9, 9, 7, 3, 27, 7, 7, 7], [14, 3, 7, 3, 27, 7, 7, 7], [21, 3, 7, 3, 27, 7, 7, 7], [3, 3, 7, 3, 27, 7, 7, 7], [14, 14, 7, 3, 3, 7, 7, 7], [14, 3, 7, 3, 5, 7, 7, 7], [14, 3, 7, 3, 3, 7, 7, 7], [14, 9, 7, 9, 3, 7, 7, 7], [14, 14, 7, 9, 3, 7, 7, 7], [14, 14, 7, 14, 3, 7, 7, 7]], "The Sunless City,Painted World of Ariamis,Iron Keep,Executioner Chariot": [[14, 10, 7, 3, 27, 7, 7, 7], [10, 10, 7, 3, 27, 7, 7, 7], [14, 21, 7, 10, 3, 7, 7, 7], [9, 10, 7, 3, 27, 7, 7, 7], [14, 10, 7, 3, 5, 7, 7, 7], [14, 14, 7, 10, 3, 7, 7, 7], [14, 10, 7, 10, 3, 7, 7, 7], [21, 10, 7, 3, 27, 7, 7, 7], [14, 9, 7, 10, 3, 7, 7, 7], [14, 10, 7, 3, 3, 7, 7, 7], [10, 3, 7, 27, 27, 7, 7, 7], [10, 3, 7, 3, 27, 7, 7, 7]], "The Sunless City,Painted World of Ariamis,Iron Keep,Explorers": [[21, 3, 7, 26, 27, 7, 7, 7], [14, 14, 7, 3, 26, 7, 7, 7], [3, 3, 7, 26, 27, 7, 7, 7], [14, 9, 7, 3, 26, 7, 7, 7], [14, 3, 7, 26, 26, 7, 7, 7], [9, 3, 7, 26, 27, 7, 7, 7], [14, 3, 7, 26, 27, 7, 7, 7], [14, 3, 7, 3, 26, 7, 7, 7], [14, 21, 7, 3, 26, 7, 7, 7]], "The Sunless City,Explorers,Executioner Chariot,Iron Keep,Painted World of Ariamis": [[10, 3, 7, 26, 27, 7, 7, 7], [14, 10, 7, 3, 26, 7, 7, 7]], "The Sunless City,Painted World of Ariamis,Darkroot": [[14, 8, 7, 22, 27, 7, 7, 7], [24, 22, 7, 22, 27, 7, 7, 7], [9, 24, 7, 22, 27, 7, 7, 7], [21, 21, 7, 24, 27, 7, 7, 7], [14, 9, 7, 8, 27, 7, 7, 7], [14, 14, 7, 21, 22, 7, 7, 7], [14, 21, 7, 22, 27, 7, 7, 7], [9, 9, 7, 8, 27, 7, 7, 7], [21, 24, 7, 22, 27, 7, 7, 7], [14, 22, 7, 27, 27, 7, 7, 7], [14, 22, 7, 22, 27, 7, 7, 7], [14, 21, 7, 21, 24, 7, 7, 7], [14, 22, 7, 22, 5, 7, 7, 7], [24, 24, 7, 22, 27, 7, 7, 7], [14, 21, 7, 9, 24, 7, 7, 7], [21, 22, 7, 22, 27, 7, 7, 7], [21, 24, 7, 27, 27, 7, 7, 7], [14, 21, 7, 9, 22, 7, 7, 7], [21, 8, 7, 24, 27, 7, 7, 7], [14, 24, 7, 22, 5, 7, 7, 7], [8, 22, 7, 27, 27, 7, 7, 7], [14, 8, 7, 22, 5, 7, 7, 7], [14, 8, 7, 24, 5, 7, 7, 7], [14, 9, 7, 24, 27, 7, 7, 7], [14, 14, 7, 9, 8, 7, 7, 7], [14, 21, 7, 8, 27, 7, 7, 7], [14, 21, 7, 8, 22, 7, 7, 7], [14, 8, 7, 22, 22, 7, 7, 7], [14, 21, 7, 8, 5, 7, 7, 7], [14, 9, 7, 9, 8, 7, 7, 7], [21, 9, 7, 8, 27, 7, 7, 7], [14, 21, 7, 24, 27, 7, 7, 7], [21, 9, 7, 22, 27, 7, 7, 7], [14, 21, 7, 21, 8, 7, 7, 7], [14, 24, 7, 24, 22, 7, 7, 7], [14, 21, 7, 22, 5, 7, 7, 7], [14, 24, 7, 22, 27, 7, 7, 7], [9, 8, 7, 22, 27, 7, 7, 7], [14, 9, 7, 8, 22, 7, 7, 7], [21, 21, 7, 22, 27, 7, 7, 7], [14, 21, 7, 9, 8, 7, 7, 7], [8, 22, 7, 22, 27, 7, 7, 7], [14, 14, 7, 8, 22, 7, 7, 7], [14, 14, 7, 8, 5, 7, 7, 7], [14, 14, 7, 8, 27, 7, 7, 7], [14, 21, 7, 24, 24, 7, 7, 7], [9, 9, 7, 24, 27, 7, 7, 7], [9, 22, 7, 27, 27, 7, 7, 7], [14, 9, 7, 9, 24, 7, 7, 7], [9, 8, 7, 8, 27, 7, 7, 7], [8, 24, 7, 27, 27, 7, 7, 7], [24, 24, 7, 27, 27, 7, 7, 7], [14, 9, 7, 8, 5, 7, 7, 7], [14, 8, 7, 24, 27, 7, 7, 7], [14, 14, 7, 24, 5, 7, 7, 7], [14, 24, 7, 22, 22, 7, 7, 7], [14, 9, 7, 22, 5, 7, 7, 7], [14, 9, 7, 24, 22, 7, 7, 7], [14, 21, 7, 8, 8, 7, 7, 7], [14, 9, 7, 24, 5, 7, 7, 7], [21, 21, 7, 8, 27, 7, 7, 7], [8, 8, 7, 24, 27, 7, 7, 7], [14, 21, 7, 24, 22, 7, 7, 7], [14, 14, 7, 22, 27, 7, 7, 7], [22, 22, 7, 22, 27, 7, 7, 7], [14, 8, 7, 27, 27, 7, 7, 7], [14, 21, 7, 22, 22, 7, 7, 7], [14, 9, 7, 22, 27, 7, 7, 7], [8, 8, 7, 22, 27, 7, 7, 7], [14, 21, 7, 21, 22, 7, 7, 7], [9, 9, 7, 22, 27, 7, 7, 7], [14, 14, 7, 9, 22, 7, 7, 7], [14, 24, 7, 24, 24, 7, 7, 7], [14, 14, 7, 21, 8, 7, 7, 7], [14, 14, 7, 24, 22, 7, 7, 7], [14, 8, 7, 8, 27, 7, 7, 7], [21, 8, 7, 22, 27, 7, 7, 7], [14, 21, 7, 8, 24, 7, 7, 7], [9, 8, 7, 27, 27, 7, 7, 7], [8, 24, 7, 22, 27, 7, 7, 7], [14, 14, 7, 24, 27, 7, 7, 7]], "The Sunless City,Executioner Chariot,Darkroot,Painted World of Ariamis": [[14, 10, 7, 24, 5, 7, 7, 7], [14, 9, 7, 10, 22, 7, 7, 7], [14, 14, 7, 10, 22, 7, 7, 7], [14, 10, 7, 8, 8, 7, 7, 7], [14, 21, 7, 10, 22, 7, 7, 7], [14, 9, 7, 10, 24, 7, 7, 7], [14, 10, 7, 24, 27, 7, 7, 7], [14, 21, 7, 10, 24, 7, 7, 7], [21, 10, 7, 22, 27, 7, 7, 7], [14, 10, 7, 8, 22, 7, 7, 7], [10, 24, 7, 22, 27, 7, 7, 7], [10, 22, 7, 22, 27, 7, 7, 7], [10, 22, 7, 27, 27, 7, 7, 7], [21, 10, 7, 8, 27, 7, 7, 7], [21, 10, 7, 24, 27, 7, 7, 7], [14, 10, 7, 10, 24, 7, 7, 7], [14, 10, 7, 24, 22, 7, 7, 7], [10, 10, 7, 22, 27, 7, 7, 7], [14, 14, 7, 10, 24, 7, 7, 7], [10, 8, 7, 24, 27, 7, 7, 7], [14, 10, 7, 22, 27, 7, 7, 7], [9, 10, 7, 8, 27, 7, 7, 7], [10, 24, 7, 27, 27, 7, 7, 7], [10, 8, 7, 22, 27, 7, 7, 7], [14, 10, 7, 22, 5, 7, 7, 7], [14, 10, 7, 8, 27, 7, 7, 7], [14, 10, 7, 24, 24, 7, 7, 7], [10, 8, 7, 8, 27, 7, 7, 7], [10, 10, 7, 24, 27, 7, 7, 7], [14, 10, 7, 22, 22, 7, 7, 7], [14, 10, 7, 8, 24, 7, 7, 7], [9, 10, 7, 22, 27, 7, 7, 7], [14, 10, 7, 8, 5, 7, 7, 7], [14, 21, 7, 10, 8, 7, 7, 7], [10, 10, 7, 8, 27, 7, 7, 7], [14, 10, 7, 10, 22, 7, 7, 7], [14, 9, 7, 10, 8, 7, 7, 7], [14, 10, 7, 10, 8, 7, 7, 7], [10, 24, 7, 24, 27, 7, 7, 7], [14, 14, 7, 10, 8, 7, 7, 7], [10, 8, 7, 27, 27, 7, 7, 7]], "The Sunless City,Explorers,Darkroot,Painted World of Ariamis": [[14, 14, 7, 8, 26, 7, 7, 7], [21, 24, 7, 26, 27, 7, 7, 7], [14, 24, 7, 26, 27, 7, 7, 7], [14, 9, 7, 8, 26, 7, 7, 7], [14, 8, 7, 26, 27, 7, 7, 7], [22, 22, 7, 26, 27, 7, 7, 7], [21, 22, 7, 26, 27, 7, 7, 7], [14, 22, 7, 26, 26, 7, 7, 7], [14, 21, 7, 22, 26, 7, 7, 7], [14, 9, 7, 24, 26, 7, 7, 7], [9, 22, 7, 26, 27, 7, 7, 7], [14, 8, 7, 22, 26, 7, 7, 7], [14, 9, 7, 22, 26, 7, 7, 7], [14, 14, 7, 22, 26, 7, 7, 7], [14, 22, 7, 26, 27, 7, 7, 7], [14, 24, 7, 22, 26, 7, 7, 7], [24, 24, 7, 26, 27, 7, 7, 7], [14, 21, 7, 8, 26, 7, 7, 7], [21, 8, 7, 26, 27, 7, 7, 7], [14, 8, 7, 24, 26, 7, 7, 7], [14, 8, 7, 26, 26, 7, 7, 7], [8, 22, 7, 26, 27, 7, 7, 7], [14, 21, 7, 24, 26, 7, 7, 7], [24, 22, 7, 26, 27, 7, 7, 7], [9, 8, 7, 26, 27, 7, 7, 7], [14, 24, 7, 26, 26, 7, 7, 7], [14, 22, 7, 22, 26, 7, 7, 7], [9, 24, 7, 26, 27, 7, 7, 7], [14, 8, 7, 8, 26, 7, 7, 7], [14, 24, 7, 24, 26, 7, 7, 7], [14, 14, 7, 24, 26, 7, 7, 7], [8, 8, 7, 26, 27, 7, 7, 7], [8, 24, 7, 26, 27, 7, 7, 7]], "The Sunless City,Explorers,Executioner Chariot,Painted World of Ariamis,Darkroot": [[14, 10, 7, 24, 26, 7, 7, 7], [10, 24, 7, 26, 27, 7, 7, 7], [14, 10, 7, 22, 26, 7, 7, 7], [10, 22, 7, 26, 27, 7, 7, 7], [14, 10, 7, 8, 26, 7, 7, 7], [10, 8, 7, 26, 27, 7, 7, 7]], "The Sunless City,Painted World of Ariamis": [[14, 14, 7, 21, 9, 7, 7, 7], [21, 21, 7, 21, 27, 7, 7, 7], [14, 21, 7, 21, 9, 7, 7, 7], [14, 21, 7, 27, 5, 7, 7, 7], [14, 14, 7, 21, 21, 7, 7, 7], [14, 14, 7, 9, 27, 7, 7, 7], [14, 21, 7, 9, 9, 7, 7, 7], [14, 14, 7, 9, 5, 7, 7, 7], [14, 21, 7, 21, 21, 7, 7, 7], [14, 14, 7, 21, 27, 7, 7, 7], [21, 9, 7, 27, 5, 7, 7, 7], [14, 21, 7, 21, 5, 7, 7, 7], [14, 21, 7, 21, 27, 7, 7, 7], [14, 21, 7, 9, 5, 7, 7, 7], [14, 14, 7, 14, 9, 7, 7, 7], [9, 9, 7, 27, 5, 7, 7, 7], [14, 9, 7, 27, 27, 7, 7, 7], [14, 21, 7, 27, 27, 7, 7, 7], [21, 9, 7, 27, 27, 7, 7, 7], [21, 21, 7, 27, 5, 7, 7, 7], [14, 21, 7, 9, 27, 7, 7, 7], [14, 9, 7, 9, 27, 7, 7, 7], [21, 21, 7, 9, 27, 7, 7, 7], [14, 14, 7, 21, 5, 7, 7, 7], [14, 14, 7, 27, 5, 7, 7, 7], [14, 14, 7, 27, 27, 7, 7, 7], [21, 21, 7, 27, 27, 7, 7, 7], [14, 9, 7, 9, 5, 7, 7, 7], [21, 9, 7, 9, 27, 7, 7, 7], [14, 14, 7, 14, 21, 7, 7, 7], [14, 14, 7, 9, 9, 7, 7, 7], [14, 9, 7, 27, 5, 7, 7, 7], [14, 14, 7, 14, 27, 7, 7, 7]], "The Sunless City,Painted World of Ariamis,Executioner Chariot": [[14, 14, 7, 21, 10, 7, 7, 7], [21, 10, 7, 27, 27, 7, 7, 7], [21, 9, 7, 10, 27, 7, 7, 7], [14, 9, 7, 9, 10, 7, 7, 7], [14, 21, 7, 9, 10, 7, 7, 7], [9, 10, 7, 27, 27, 7, 7, 7], [14, 21, 7, 10, 27, 7, 7, 7], [14, 14, 7, 10, 5, 7, 7, 7], [14, 10, 7, 10, 27, 7, 7, 7], [14, 9, 7, 10, 27, 7, 7, 7], [14, 10, 7, 27, 5, 7, 7, 7], [14, 14, 7, 14, 10, 7, 7, 7], [14, 21, 7, 10, 5, 7, 7, 7], [14, 10, 7, 10, 5, 7, 7, 7], [14, 21, 7, 21, 10, 7, 7, 7], [14, 9, 7, 10, 10, 7, 7, 7], [14, 10, 7, 27, 27, 7, 7, 7], [14, 14, 7, 9, 10, 7, 7, 7], [14, 9, 7, 10, 5, 7, 7, 7], [21, 10, 7, 10, 27, 7, 7, 7], [14, 21, 7, 10, 10, 7, 7, 7], [14, 14, 7, 10, 27, 7, 7, 7], [21, 21, 7, 10, 27, 7, 7, 7], [14, 14, 7, 10, 10, 7, 7, 7], [9, 10, 7, 10, 27, 7, 7, 7], [9, 9, 7, 10, 27, 7, 7, 7], [10, 10, 7, 27, 27, 7, 7, 7]], "The Sunless City,Painted World of Ariamis,Explorers": [[21, 21, 7, 26, 27, 7, 7, 7], [14, 9, 7, 26, 5, 7, 7, 7], [14, 9, 7, 9, 26, 7, 7, 7], [14, 21, 7, 26, 27, 7, 7, 7], [14, 14, 7, 9, 26, 7, 7, 7], [14, 21, 7, 9, 26, 7, 7, 7], [14, 9, 7, 26, 27, 7, 7, 7], [14, 14, 7, 26, 27, 7, 7, 7], [14, 14, 7, 26, 26, 7, 7, 7], [14, 9, 7, 26, 26, 7, 7, 7], [14, 21, 7, 21, 26, 7, 7, 7], [14, 14, 7, 21, 26, 7, 7, 7], [21, 9, 7, 26, 27, 7, 7, 7], [14, 21, 7, 26, 5, 7, 7, 7], [14, 14, 7, 26, 5, 7, 7, 7], [9, 9, 7, 26, 27, 7, 7, 7], [14, 14, 7, 14, 26, 7, 7, 7], [14, 21, 7, 26, 26, 7, 7, 7]], "The Sunless City,Painted World of Ariamis,Explorers,Executioner Chariot": [[14, 14, 7, 10, 26, 7, 7, 7], [14, 10, 7, 10, 26, 7, 7, 7], [14, 10, 7, 26, 27, 7, 7, 7], [10, 10, 7, 26, 27, 7, 7, 7], [21, 10, 7, 26, 27, 7, 7, 7], [14, 9, 7, 10, 26, 7, 7, 7], [14, 10, 7, 26, 5, 7, 7, 7], [14, 10, 7, 26, 26, 7, 7, 7], [14, 21, 7, 10, 26, 7, 7, 7], [9, 10, 7, 26, 27, 7, 7, 7]]}}