{"enemySlots": [3, 3, 0, 0, 0, 0, 0, 0, 0, 0, 0], "alternatives": {"Dark Souls The Board Game,Painted World of Ariamis,Explorers,Darkroot": [[17, 11, 21, 16, 11, 24], [17, 6, 14, 16, 11, 21], [17, 11, 21, 16, 21, 25], [17, 6, 21, 16, 11, 24], [17, 11, 9, 16, 9, 25], [17, 6, 21, 16, 11, 8], [17, 11, 21, 16, 14, 25]], "Dark Souls The Board Game,Painted World of Ariamis,Tomb of Giants,Darkroot": [[17, 21, 28, 16, 28, 9], [17, 14, 9, 16, 28, 25], [17, 6, 28, 16, 21, 9], [17, 14, 28, 16, 28, 9], [17, 6, 21, 16, 14, 28], [17, 6, 14, 13, 6, 9], [17, 6, 21, 13, 6, 21]], "Dark Souls The Board Game,Explorers,Darkroot": [[17, 11, 14, 16, 11, 24], [17, 6, 14, 16, 11, 8], [17, 11, 14, 16, 11, 14], [17, 11, 14, 16, 11, 8], [17, 6, 14, 16, 11, 24], [17, 6, 14, 16, 11, 14], [17, 11, 14, 16, 14, 25]], "Dark Souls The Board Game,Explorers": [[16, 6, 14, 16, 11, 14], [16, 11, 14, 16, 11, 14], [16, 11, 14, 16, 14, 25]], "Dark Souls The Board Game,Tomb of Giants,Darkroot": [[17, 6, 14, 13, 6, 14], [17, 14, 28, 16, 14, 25], [17, 6, 14, 13, 14, 25], [17, 6, 28, 16, 14, 24], [17, 6, 14, 13, 14, 28], [17, 6, 14, 16, 14, 28], [17, 14, 28, 16, 14, 28]], "Dark Souls The Board Game,Painted World of Ariamis,Explorers": [[16, 11, 21, 16, 11, 21], [16, 6, 14, 16, 11, 21], [16, 6, 14, 16, 11, 9], [16, 6, 21, 16, 11, 9], [16, 11, 14, 16, 11, 21], [16, 11, 21, 16, 11, 9], [16, 11, 21, 16, 14, 25]], "Painted World of Ariamis,Tomb of Giants,Explorers,Darkroot": [[17, 11, 21, 13, 11, 9], [17, 11, 21, 13, 11, 21], [17, 11, 21, 13, 21, 28]], "Painted World of Ariamis,Explorers,Darkroot,Dark Souls The Board Game,Tomb of Giants": [[17, 11, 21, 16, 21, 28], [17, 6, 14, 13, 11, 9], [17, 11, 14, 13, 11, 21], [17, 6, 21, 13, 11, 9], [17, 6, 14, 13, 11, 21], [17, 11, 28, 16, 21, 9], [17, 11, 14, 13, 11, 9]], "Painted World of Ariamis,Tomb of Giants,Explorers,Dark Souls The Board Game": [[16, 11, 21, 16, 21, 28], [16, 11, 21, 16, 14, 28], [16, 11, 28, 16, 21, 9], [16, 11, 28, 16, 14, 9]], "Dark Souls The Board Game,Painted World of Ariamis,Darkroot": [[17, 6, 21, 16, 6, 9], [17, 6, 21, 16, 14, 25], [17, 6, 14, 16, 6, 21], [17, 14, 25, 16, 21, 25], [17, 6, 9, 16, 6, 9], [17, 6, 21, 16, 6, 8], [17, 6, 14, 20, 6, 21]], "Dark Souls The Board Game,Painted World of Ariamis,Tomb of Giants": [[16, 6, 28, 16, 14, 9], [16, 6, 21, 16, 14, 28], [16, 6, 21, 16, 21, 28], [16, 6, 28, 16, 21, 9]], "Dark Souls The Board Game,Tomb of Giants,Explorers,Darkroot": [[17, 6, 14, 13, 11, 14], [17, 11, 14, 13, 14, 28], [17, 11, 14, 13, 11, 14], [17, 11, 14, 16, 14, 28]], "Dark Souls The Board Game,Tomb of Giants": [[16, 6, 14, 13, 6, 14], [16, 6, 14, 16, 14, 28]], "Dark Souls The Board Game,Darkroot": [[17, 6, 14, 16, 6, 8], [17, 6, 14, 16, 6, 14], [17, 6, 14, 16, 6, 22], [17, 6, 14, 16, 6, 24], [17, 6, 14, 16, 14, 25], [17, 14, 25, 16, 14, 25]], "Dark Souls The Board Game,Painted World of Ariamis": [[16, 6, 21, 16, 6, 21], [16, 6, 21, 16, 14, 25], [16, 6, 9, 16, 6, 9], [16, 6, 14, 16, 6, 9], [16, 6, 21, 16, 21, 25], [16, 6, 14, 16, 6, 21], [16, 6, 21, 16, 6, 9]], "Dark Souls The Board Game,Iron Keep,Darkroot": [[17, 6, 14, 16, 6, 3]], "Dark Souls The Board Game": [[16, 6, 14, 16, 6, 14], [16, 6, 14, 16, 14, 25]], "Dark Souls The Board Game,Tomb of Giants,Explorers": [[16, 11, 14, 16, 14, 28], [16, 6, 14, 13, 11, 14]], "The Sunless City,Painted World of Ariamis,Explorers,Darkroot": [[17, 11, 21, 16, 11, 24], [17, 6, 14, 16, 11, 21], [17, 11, 21, 16, 21, 25], [17, 6, 21, 16, 11, 24], [17, 11, 9, 16, 9, 25], [17, 6, 21, 16, 11, 8], [17, 11, 21, 16, 14, 25]], "The Sunless City,Painted World of Ariamis,Tomb of Giants,Darkroot": [[17, 21, 28, 16, 28, 9], [17, 14, 9, 16, 28, 25], [17, 6, 28, 16, 21, 9], [17, 14, 28, 16, 28, 9], [17, 6, 21, 16, 14, 28], [17, 6, 14, 13, 6, 9], [17, 6, 21, 13, 6, 21]], "The Sunless City,Explorers,Darkroot": [[17, 11, 14, 16, 11, 24], [17, 6, 14, 16, 11, 8], [17, 11, 14, 16, 11, 14], [17, 11, 14, 16, 11, 8], [17, 6, 14, 16, 11, 24], [17, 6, 14, 16, 11, 14], [17, 11, 14, 16, 14, 25]], "The Sunless City,Explorers": [[16, 6, 14, 16, 11, 14], [16, 11, 14, 16, 11, 14], [16, 11, 14, 16, 14, 25]], "The Sunless City,Tomb of Giants,Darkroot": [[17, 6, 14, 13, 6, 14], [17, 14, 28, 16, 14, 25], [17, 6, 14, 13, 14, 25], [17, 6, 28, 16, 14, 24], [17, 6, 14, 13, 14, 28], [17, 6, 14, 16, 14, 28], [17, 14, 28, 16, 14, 28]], "The Sunless City,Painted World of Ariamis,Explorers": [[16, 11, 21, 16, 11, 21], [16, 6, 14, 16, 11, 21], [16, 6, 14, 16, 11, 9], [16, 6, 21, 16, 11, 9], [16, 11, 14, 16, 11, 21], [16, 11, 21, 16, 11, 9], [16, 11, 21, 16, 14, 25]], "Painted World of Ariamis,Explorers,Darkroot,The Sunless City,Tomb of Giants": [[17, 11, 21, 16, 21, 28], [17, 6, 14, 13, 11, 9], [17, 11, 14, 13, 11, 21], [17, 6, 21, 13, 11, 9], [17, 6, 14, 13, 11, 21], [17, 11, 28, 16, 21, 9], [17, 11, 14, 13, 11, 9]], "Painted World of Ariamis,Tomb of Giants,Explorers,The Sunless City": [[16, 11, 21, 16, 21, 28], [16, 11, 21, 16, 14, 28], [16, 11, 28, 16, 21, 9], [16, 11, 28, 16, 14, 9]], "The Sunless City,Painted World of Ariamis,Darkroot": [[17, 6, 21, 16, 6, 9], [17, 6, 21, 16, 14, 25], [17, 6, 14, 16, 6, 21], [17, 14, 25, 16, 21, 25], [17, 6, 9, 16, 6, 9], [17, 6, 21, 16, 6, 8], [17, 6, 14, 20, 6, 21]], "The Sunless City,Painted World of Ariamis,Tomb of Giants": [[16, 6, 28, 16, 14, 9], [16, 6, 21, 16, 14, 28], [16, 6, 21, 16, 21, 28], [16, 6, 28, 16, 21, 9]], "The Sunless City,Tomb of Giants,Explorers,Darkroot": [[17, 6, 14, 13, 11, 14], [17, 11, 14, 13, 14, 28], [17, 11, 14, 13, 11, 14], [17, 11, 14, 16, 14, 28]], "The Sunless City,Tomb of Giants": [[16, 6, 14, 13, 6, 14], [16, 6, 14, 16, 14, 28]], "The Sunless City,Darkroot": [[17, 6, 14, 16, 6, 8], [17, 6, 14, 16, 6, 14], [17, 6, 14, 16, 6, 22], [17, 6, 14, 16, 6, 24], [17, 6, 14, 16, 14, 25], [17, 14, 25, 16, 14, 25]], "The Sunless City,Painted World of Ariamis": [[16, 6, 21, 16, 6, 21], [16, 6, 21, 16, 14, 25], [16, 6, 9, 16, 6, 9], [16, 6, 14, 16, 6, 9], [16, 6, 21, 16, 21, 25], [16, 6, 14, 16, 6, 21], [16, 6, 21, 16, 6, 9]], "The Sunless City,Iron Keep,Darkroot": [[17, 6, 14, 16, 6, 3]], "The Sunless City": [[16, 6, 14, 16, 6, 14], [16, 6, 14, 16, 14, 25]], "The Sunless City,Tomb of Giants,Explorers": [[16, 11, 14, 16, 14, 28], [16, 6, 14, 13, 11, 14]]}}