{"enemySlots": [1, 2, 0, 0, 0, 0, 0, 0, 0, 0, 0], "alternatives": {"Painted World of Ariamis,Executioner Chariot": [[9, 10, 10], [9, 9, 10]], "Executioner Chariot,Darkroot": [[8, 10, 10], [24, 24, 10], [22, 10, 10]], "Tomb of Giants,Executioner Chariot,Darkroot": [[22, 10, 30], [24, 10, 30]], "Darkroot": [[24, 22, 8], [24, 24, 8], [22, 22, 8]], "Tomb of Giants,Darkroot": [[22, 8, 30], [24, 24, 30], [8, 8, 30]], "Painted World of Ariamis,Darkroot": [[9, 24, 22], [9, 9, 8], [9, 22, 8]], "Painted World of Ariamis,Executioner Chariot,Darkroot": [[9, 24, 10], [9, 8, 10], [9, 22, 10]], "Executioner Chariot,Explorers,Dark Souls The Board Game": [[14, 10, 26]], "Painted World of Ariamis,Dark Souls The Board Game,Iron Keep": [[14, 9, 3], [14, 21, 3]], "Explorers,Darkroot,Dark Souls The Board Game": [[14, 8, 26], [14, 24, 26], [14, 22, 26]], "Tomb of Giants,Dark Souls The Board Game": [[14, 30, 30]], "Painted World of Ariamis,Explorers,Darkroot": [[21, 24, 26], [21, 8, 26], [21, 22, 26]], "Painted World of Ariamis,Dark Souls The Board Game": [[14, 21, 27], [21, 21, 27]], "Painted World of Ariamis,Iron Keep": [[21, 9, 3], [21, 21, 3]], "Painted World of Ariamis,Tomb of Giants": [[9, 9, 30], [21, 30, 30]], "Dark Souls The Board Game,Iron Keep": [[14, 14, 3]], "Painted World of Ariamis,Executioner Chariot,Tomb of Giants": [[9, 10, 30], [21, 10, 30]], "Painted World of Ariamis,Explorers,Dark Souls The Board Game": [[14, 9, 26]], "Dark Souls The Board Game": [[14, 14, 27]], "Painted World of Ariamis,Explorers": [[21, 9, 26]], "Painted World of Ariamis,Executioner Chariot,Explorers": [[21, 10, 26]], "Painted World of Ariamis,Darkroot,Tomb of Giants": [[9, 8, 30], [9, 22, 30], [9, 24, 30]], "Executioner Chariot,Explorers,The Sunless City": [[14, 10, 26]], "Painted World of Ariamis,The Sunless City,Iron Keep": [[14, 9, 3], [14, 21, 3]], "Explorers,Darkroot,The Sunless City": [[14, 8, 26], [14, 24, 26], [14, 22, 26]], "Tomb of Giants,The Sunless City": [[14, 30, 30]], "Painted World of Ariamis,The Sunless City": [[14, 21, 27], [21, 21, 27]], "The Sunless City,Iron Keep": [[14, 14, 3]], "Painted World of Ariamis,Explorers,The Sunless City": [[14, 9, 26]], "The Sunless City": [[14, 14, 27]]}, "original": [24, 22, 8]}