{"enemySlots": [2, 2, 0, 0, 0, 0, 0, 0, 0, 0, 0], "alternatives": {"Painted World of Ariamis,Tomb of Giants,Dark Souls The Board Game": [[13, 14, 21, 21], [13, 14, 14, 21]], "Darkroot,Executioner Chariot,Dark Souls The Board Game": [[17, 14, 14, 10]], "Darkroot,Painted World of Ariamis": [[17, 21, 22, 22], [17, 21, 21, 9]], "Darkroot,Dark Souls The Board Game": [[17, 14, 24, 22], [17, 14, 14, 22]], "Darkroot,Painted World of Ariamis,Dark Souls The Board Game": [[17, 14, 9, 9], [17, 14, 9, 24]], "Dark Souls The Board Game": [[16, 14, 14, 14]], "Painted World of Ariamis,Tomb of Giants": [[13, 21, 21, 21]], "Painted World of Ariamis,Dark Souls The Board Game": [[16, 21, 21, 21], [16, 14, 14, 21]], "Tomb of Giants,Dark Souls The Board Game": [[13, 14, 14, 14]], "Darkroot,Executioner Chariot,Painted World of Ariamis": [[17, 21, 21, 10]], "Darkroot,Executioner Chariot,Painted World of Ariamis,Dark Souls The Board Game": [[17, 14, 21, 10]], "Iron Keep,Darkroot,Dark Souls The Board Game": [[17, 14, 14, 3]], "Iron Keep,Darkroot,Painted World of Ariamis,Dark Souls The Board Game": [[17, 14, 21, 3]], "Iron Keep,Darkroot,Painted World of Ariamis": [[17, 21, 21, 3]], "Painted World of Ariamis,Tomb of Giants,The Sunless City": [[13, 14, 21, 21], [13, 14, 14, 21]], "Darkroot,Executioner Chariot,The Sunless City": [[17, 14, 14, 10]], "Darkroot,The Sunless City": [[17, 14, 24, 22], [17, 14, 14, 22]], "Darkroot,Painted World of Ariamis,The Sunless City": [[17, 14, 9, 9], [17, 14, 9, 24]], "The Sunless City": [[16, 14, 14, 14]], "Painted World of Ariamis,The Sunless City": [[16, 21, 21, 21], [16, 14, 14, 21]], "Tomb of Giants,The Sunless City": [[13, 14, 14, 14]], "Darkroot,Executioner Chariot,Painted World of Ariamis,The Sunless City": [[17, 14, 21, 10]], "Iron Keep,Darkroot,The Sunless City": [[17, 14, 14, 3]], "Iron Keep,Darkroot,Painted World of Ariamis,The Sunless City": [[17, 14, 21, 3]]}}