{"enemySlots": [1, 1, 0, 0, 0, 0, 0, 0, 0, 0, 0], "alternatives": {"Tomb of Giants": [[13, 30]], "Dark Souls The Board Game,Painted World of Ariamis": [[16, 9]], "Dark Souls The Board Game,Tomb of Giants": [[13, 14]], "Painted World of Ariamis,Tomb of Giants": [[13, 21]], "Darkroot": [[17, 8]], "Darkroot,Iron Keep": [[17, 3]], "Darkroot,Dark Souls The Board Game": [[16, 24]], "Executioner Chariot,Tomb of Giants": [[13, 10]], "Executioner Chariot,Painted World of Ariamis": [[20, 10]], "The Sunless City,Painted World of Ariamis": [[16, 9]], "The Sunless City,Tomb of Giants": [[13, 14]], "Darkroot,The Sunless City": [[16, 24]]}}