{"enemySlots": [1, 1, 0, 0, 0, 0, 0, 0, 0, 0, 0], "alternatives": {"Tomb of Giants": [[13, 30]], "Explorers,Dark Souls The Board Game": [[16, 26]], "Tomb of Giants,Painted World of Ariamis": [[13, 9]], "Darkroot": [[17, 8]], "Darkroot,Executioner Chariot": [[17, 10]], "Painted World of Ariamis,Dark Souls The Board Game": [[20, 14]], "Iron Keep,Dark Souls The Board Game": [[16, 3]], "Tomb of Giants,Executioner Chariot": [[13, 10]], "Tomb of Giants,Darkroot": [[13, 22]], "Painted World of Ariamis": [[20, 21]], "Darkroot,Painted World of Ariamis": [[17, 9]], "Dark Souls The Board Game": [[16, 27]], "Explorers,The Sunless City": [[16, 26]], "Painted World of Ariamis,The Sunless City": [[20, 14]], "Iron Keep,The Sunless City": [[16, 3]], "The Sunless City": [[16, 27]]}, "original": [17, 8]}