{"enemySlots": [2, 1, 0, 0, 0, 0, 0, 0, 0, 0, 0], "alternatives": {"Dark Souls The Board Game,Tomb of Giants": [[28, 25, 13]], "Dark Souls The Board Game,Iron Keep": [[1, 1, 16]], "Painted World of Ariamis,Tomb of Giants,Darkroot": [[31, 8, 19]], "Explorers,Iron Keep,Painted World of Ariamis": [[11, 1, 20]], "Dark Souls The Board Game,Tomb of Giants,Painted World of Ariamis": [[28, 25, 20]], "Phantoms,Tomb of Giants,Painted World of Ariamis": [[21, 28, 46]], "Dark Souls The Board Game,Iron Keep,Tomb of Giants": [[25, 3, 19]], "Phantoms,Executioner Chariot,Tomb of Giants": [[10, 28, 46]], "Explorers,Painted World of Ariamis": [[11, 11, 20]], "Phantoms,Explorers,Tomb of Giants": [[30, 11, 43]], "Phantoms,Explorers,Painted World of Ariamis": [[21, 11, 46]], "Explorers,Iron Keep,Tomb of Giants": [[11, 1, 13]], "Dark Souls The Board Game,Explorers,Iron Keep": [[11, 1, 16]], "Dark Souls The Board Game,Explorers,Tomb of Giants": [[11, 19, 27]], "Dark Souls The Board Game,Phantoms,Tomb of Giants": [[30, 6, 43]], "Tomb of Giants": [[28, 28, 13]], "Dark Souls The Board Game,Phantoms,Executioner Chariot": [[10, 6, 46]], "Dark Souls The Board Game,Phantoms,Painted World of Ariamis": [[6, 21, 46]], "Dark Souls The Board Game,Explorers": [[11, 25, 16]], "Dark Souls The Board Game,Iron Keep,Painted World of Ariamis": [[6, 1, 20]], "Dark Souls The Board Game,Painted World of Ariamis,Darkroot": [[25, 31, 17]], "Dark Souls The Board Game,Explorers,Painted World of Ariamis": [[11, 31, 16]], "Dark Souls The Board Game,Phantoms,Explorers": [[14, 11, 46]], "Explorers,Tomb of Giants,Painted World of Ariamis": [[11, 28, 20]], "Painted World of Ariamis,Iron Keep,Tomb of Giants": [[31, 3, 19]], "Iron Keep,Tomb of Giants": [[28, 1, 13]], "Dark Souls The Board Game,Painted World of Ariamis": [[6, 25, 20]], "Dark Souls The Board Game,Phantoms": [[14, 6, 46]], "Phantoms,Tomb of Giants": [[30, 28, 46]], "Dark Souls The Board Game": [[25, 25, 16]], "Explorers,Tomb of Giants": [[11, 19, 26]], "Painted World of Ariamis,Iron Keep,Darkroot": [[1, 31, 17]], "Painted World of Ariamis,Darkroot": [[31, 31, 17]], "Phantoms,Explorers,Executioner Chariot": [[10, 11, 46]], "Tomb of Giants,Painted World of Ariamis": [[28, 28, 20]], "The Sunless City,Tomb of Giants": [[28, 25, 13]], "The Sunless City,Iron Keep": [[1, 1, 16]], "The Sunless City,Tomb of Giants,Painted World of Ariamis": [[28, 25, 20]], "The Sunless City,Iron Keep,Tomb of Giants": [[25, 3, 19]], "The Sunless City,Explorers,Iron Keep": [[11, 1, 16]], "The Sunless City,Explorers,Tomb of Giants": [[11, 19, 27]], "The Sunless City,Phantoms,Tomb of Giants": [[30, 6, 43]], "The Sunless City,Phantoms,Executioner Chariot": [[10, 6, 46]], "The Sunless City,Phantoms,Painted World of Ariamis": [[6, 21, 46]], "The Sunless City,Explorers": [[11, 25, 16]], "The Sunless City,Iron Keep,Painted World of Ariamis": [[6, 1, 20]], "The Sunless City,Painted World of Ariamis,Darkroot": [[25, 31, 17]], "The Sunless City,Explorers,Painted World of Ariamis": [[11, 31, 16]], "The Sunless City,Phantoms,Explorers": [[14, 11, 46]], "The Sunless City,Painted World of Ariamis": [[6, 25, 20]], "The Sunless City,Phantoms": [[14, 6, 46]], "The Sunless City": [[25, 25, 16]]}}